{"skeleton":{"hash":"r9msgVb3tNrHA0ysUFhzM0/pf1A","spine":"3.6.53","width":2187.49,"height":2069.52,"images":""},"bones":[{"name":"root"},{"name":"hit","parent":"root","x":-369.15,"y":-606.46},{"name":"蝴蝶群","parent":"hit","color":"ff00e1ff"},{"name":"蝴蝶1","parent":"蝴蝶群","rotation":-17.24,"x":105.99,"y":7},{"name":"bone2","parent":"蝴蝶1","length":32.34,"rotation":-173.68,"x":-0.98,"y":0.61},{"name":"bone3","parent":"蝴蝶1","length":30.8,"rotation":169.94,"x":-0.11,"y":0.36},{"name":"蝴蝶2","parent":"蝴蝶群","rotation":49.37,"x":337.26,"y":-0.02},{"name":"bone4","parent":"蝴蝶2","length":17.28,"rotation":-15.98,"x":0.34,"y":-0.14},{"name":"bone5","parent":"蝴蝶2","length":16.98,"rotation":4.86,"x":0.14,"y":0.34},{"name":"蝴蝶3","parent":"蝴蝶群","rotation":49.37,"x":296.39,"y":-0.02},{"name":"bone6","parent":"蝴蝶3","length":17.28,"rotation":-15.98,"x":4.2,"y":3.17},{"name":"bone7","parent":"蝴蝶3","length":16.98,"rotation":4.86,"x":4,"y":3.65},{"name":"蝴蝶5","parent":"蝴蝶群","rotation":49.37,"x":214,"y":-0.02},{"name":"bone10","parent":"蝴蝶5","length":17.28,"rotation":-15.98,"x":0.34,"y":-0.14},{"name":"bone11","parent":"蝴蝶5","length":16.98,"rotation":4.86,"x":0.14,"y":0.34},{"name":"蝴蝶6","parent":"蝴蝶群","rotation":49.37,"x":170.84,"y":-0.02},{"name":"bone12","parent":"蝴蝶6","length":17.28,"rotation":-15.98,"x":0.34,"y":-0.14},{"name":"bone13","parent":"蝴蝶6","length":16.98,"rotation":4.86,"x":0.14,"y":0.34},{"name":"蝴蝶7","parent":"蝴蝶群","rotation":-17.24,"x":-90.42,"y":7},{"name":"bone14","parent":"蝴蝶7","length":32.34,"rotation":-173.68,"x":-0.98,"y":0.61},{"name":"bone15","parent":"蝴蝶7","length":30.8,"rotation":169.94,"x":-0.11,"y":0.36},{"name":"蝴蝶8","parent":"蝴蝶群","rotation":-17.24,"x":-41.07,"y":7},{"name":"bone16","parent":"蝴蝶8","length":32.34,"rotation":-173.68,"x":-0.98,"y":0.61},{"name":"bone17","parent":"蝴蝶8","length":30.8,"rotation":169.94,"x":-0.11,"y":0.36},{"name":"蝴蝶9","parent":"蝴蝶群","rotation":57.08,"x":9.64,"y":7,"shearX":-180},{"name":"bone18","parent":"蝴蝶9","length":32.34,"rotation":-173.68,"x":-0.98,"y":0.61},{"name":"bone19","parent":"蝴蝶9","length":30.8,"rotation":169.94,"x":-0.11,"y":0.36},{"name":"蝴蝶10","parent":"蝴蝶群","rotation":-17.24,"x":58.99,"y":7},{"name":"bone20","parent":"蝴蝶10","length":32.34,"rotation":-173.68,"x":-0.98,"y":0.61},{"name":"bone21","parent":"蝴蝶10","length":30.8,"rotation":169.94,"x":-0.11,"y":0.36},{"name":"光圈","parent":"hit","x":373.52,"y":734.72},{"name":"光束群","parent":"hit","x":361.77,"y":763.2,"color":"0002ffff"},{"name":"光束","parent":"光束群","x":-205.63,"y":10.89},{"name":"光束2","parent":"光束群","x":231.94,"y":8.02},{"name":"光束3","parent":"光束群","x":-129.15,"y":10.89},{"name":"光束4","parent":"光束群","x":-50.71,"y":10.89},{"name":"光束5","parent":"光束群","x":141.73,"y":8.02},{"name":"光束6","parent":"光束群","x":43.68,"y":8.02},{"name":"光柱群","parent":"hit","x":361.77,"y":763.2,"color":"feff00ff"},{"name":"光柱","parent":"光柱群","x":6.43,"y":-124.36,"scaleY":30},{"name":"光柱2","parent":"hit","x":930.79,"y":638.84,"scaleX":0.467,"scaleY":30},{"name":"光柱3","parent":"hit","x":-209.06,"y":638.84,"scaleX":0.684,"scaleY":30},{"name":"光柱4","parent":"hit","x":1231.69,"y":638.84,"scaleX":0.963,"scaleY":30},{"name":"光柱5","parent":"hit","x":-551.76,"y":638.84,"scaleX":0.398,"scaleY":30},{"name":"晋升成功","parent":"hit","x":364.63,"y":770.82,"color":"ff0000ff"},{"name":"功","parent":"晋升成功","x":165.37,"y":-7.82},{"name":"功2","parent":"晋升成功","x":165.37,"y":-7.82},{"name":"升","parent":"晋升成功","x":-54.63,"y":-7.82},{"name":"升2","parent":"晋升成功","x":-54.63,"y":-7.82},{"name":"成","parent":"晋升成功","x":55.37,"y":-7.82},{"name":"成2","parent":"晋升成功","x":55.37,"y":-7.82},{"name":"星星","parent":"hit","x":452.8,"y":729.62,"color":"06ff00ff"},{"name":"晋","parent":"晋升成功","x":-164.63,"y":-7.82},{"name":"晋2","parent":"晋升成功","x":-164.63,"y":-7.82},{"name":"条幅","parent":"晋升成功","x":6.82,"y":-7.87},{"name":"花瓣群","parent":"hit","x":361.77,"y":763.2,"color":"000000ff"},{"name":"花瓣","parent":"花瓣群","x":-176.6,"y":583.94},{"name":"花瓣2","parent":"花瓣群","rotation":-21.99,"x":-36.64,"y":583.94},{"name":"花瓣3","parent":"花瓣群","rotation":27.38,"x":139.14,"y":583.94},{"name":"花瓣4","parent":"花瓣群","rotation":24.84,"x":-137.35,"y":583.94},{"name":"花瓣5","parent":"花瓣群","rotation":69.45,"x":52.32,"y":583.94},{"name":"花瓣6","parent":"花瓣群","rotation":-55.13,"x":-8.12,"y":583.94},{"name":"花瓣7","parent":"花瓣群","rotation":-41.44,"x":189.98,"y":583.94},{"name":"花瓣8","parent":"花瓣群","rotation":161.72,"x":18.53,"y":583.94},{"name":"花瓣9","parent":"花瓣群","rotation":31.91,"x":-155.21,"y":583.94},{"name":"闪光点2","parent":"星星","x":-22.48,"y":38.66,"scaleX":0.25,"scaleY":0.25},{"name":"闪光点3","parent":"星星","x":8.58,"y":181.76,"scaleX":0.45,"scaleY":0.45},{"name":"闪光点4","parent":"星星","x":-183.51,"y":-54.5,"scaleX":0.55,"scaleY":0.55},{"name":"闪光点5","parent":"星星","x":128,"y":-160,"scaleX":0.35,"scaleY":0.35},{"name":"闪光点6","parent":"星星","x":180.8,"y":-2.69,"scaleX":0.8,"scaleY":0.8},{"name":"闪光点7","parent":"星星","x":8.35,"y":-5.09,"scaleX":0.7,"scaleY":0.7},{"name":"闪光点8","parent":"星星","x":152,"y":111,"scaleX":0.4,"scaleY":0.4},{"name":"闪光点9","parent":"星星","x":-125.78,"y":132.21,"scaleX":0.3,"scaleY":0.3},{"name":"闪光点10","parent":"星星","x":-89,"y":-171,"scaleX":0.35,"scaleY":0.35},{"name":"闪光点11","parent":"星星","x":59.94,"y":-155.62,"scaleX":0.7,"scaleY":0.7},{"name":"闪光点12","parent":"星星","x":-18.52,"y":-94.73,"scaleX":0.5,"scaleY":0.5},{"name":"闪光点13","parent":"星星","x":-98.61,"y":-19.92,"scaleX":0.2,"scaleY":0.2},{"name":"闪光点14","parent":"星星","x":88.22,"y":-62.87,"scaleX":0.2,"scaleY":0.2},{"name":"闪光点15","parent":"星星","x":-125.28,"y":86.03,"scaleX":0.5,"scaleY":0.5},{"name":"闪光点16","parent":"星星","x":67.17,"y":85.94,"scaleX":0.3,"scaleY":0.3}],"slots":[{"name":"光柱","bone":"光柱","attachment":"光柱"},{"name":"光柱2","bone":"光柱2","attachment":"光柱"},{"name":"光柱3","bone":"光柱3","attachment":"光柱"},{"name":"光柱5","bone":"光柱5","attachment":"光柱"},{"name":"光柱4","bone":"光柱4","attachment":"光柱"},{"name":"光束","bone":"光束","attachment":"光束"},{"name":"光束3","bone":"光束3","attachment":"光束"},{"name":"光束4","bone":"光束4","attachment":"光束"},{"name":"光束2","bone":"光束2","attachment":"光束2"},{"name":"光束5","bone":"光束5","attachment":"光束2"},{"name":"光束6","bone":"光束6","attachment":"光束2"},{"name":"huaban1","bone":"花瓣","attachment":"huaban1"},{"name":"huaban6","bone":"花瓣6","attachment":"huaban1"},{"name":"huaban4","bone":"花瓣4","attachment":"huaban1"},{"name":"huaban5","bone":"花瓣5","attachment":"huaban1"},{"name":"huaban2","bone":"花瓣2","attachment":"huaban1"},{"name":"huaban3","bone":"花瓣3","attachment":"huaban1"},{"name":"huaban7","bone":"花瓣7","attachment":"huaban1"},{"name":"huaban8","bone":"花瓣8","attachment":"huaban1"},{"name":"huaban9","bone":"花瓣9","attachment":"huaban1"},{"name":"闪光3","bone":"闪光点2","attachment":"闪光"},{"name":"闪光14","bone":"闪光点13","attachment":"闪光"},{"name":"闪光17","bone":"闪光点16","attachment":"闪光"},{"name":"闪光4","bone":"闪光点3","attachment":"闪光"},{"name":"闪光5","bone":"闪光点4","attachment":"闪光"},{"name":"闪光6","bone":"闪光点5","attachment":"闪光"},{"name":"闪光7","bone":"闪光点6","attachment":"闪光"},{"name":"闪光15","bone":"闪光点14","attachment":"闪光"},{"name":"闪光8","bone":"闪光点7","attachment":"闪光"},{"name":"闪光16","bone":"闪光点15","attachment":"闪光"},{"name":"闪光13","bone":"闪光点12","attachment":"闪光"},{"name":"闪光9","bone":"闪光点8","attachment":"闪光"},{"name":"闪光10","bone":"闪光点9","attachment":"闪光"},{"name":"闪光11","bone":"闪光点10","attachment":"闪光"},{"name":"闪光12","bone":"闪光点11","attachment":"闪光"},{"name":"蝴蝶2-2","bone":"bone5","attachment":"蝴蝶2-2"},{"name":"蝴蝶2-4","bone":"bone7","attachment":"蝴蝶2-2"},{"name":"蝴蝶2-8","bone":"bone11","attachment":"蝴蝶2-2"},{"name":"蝴蝶2-10","bone":"bone13","attachment":"蝴蝶2-2"},{"name":"蝴蝶1-4","bone":"bone15","attachment":"蝴蝶1-2"},{"name":"蝴蝶1-6","bone":"bone17","attachment":"蝴蝶1-2"},{"name":"蝴蝶1-8","bone":"bone19","attachment":"蝴蝶1-2"},{"name":"蝴蝶1-10","bone":"bone21","attachment":"蝴蝶1-2"},{"name":"蝴蝶2-9","bone":"bone12","attachment":"蝴蝶2-1"},{"name":"蝴蝶1-9","bone":"蝴蝶10","attachment":"蝴蝶1-1"},{"name":"蝴蝶2-7","bone":"bone10","attachment":"蝴蝶2-1"},{"name":"蝴蝶6","bone":"蝴蝶6","attachment":"蝴蝶2"},{"name":"蝴蝶1-7","bone":"蝴蝶9","attachment":"蝴蝶1-1"},{"name":"蝴蝶10","bone":"bone20","attachment":"蝴蝶1"},{"name":"蝴蝶1-5","bone":"蝴蝶8","attachment":"蝴蝶1-1"},{"name":"蝴蝶2-3","bone":"bone6","attachment":"蝴蝶2-1"},{"name":"蝴蝶5","bone":"蝴蝶5","attachment":"蝴蝶2"},{"name":"蝴蝶1-3","bone":"蝴蝶7","attachment":"蝴蝶1-1"},{"name":"蝴蝶9","bone":"bone18","attachment":"蝴蝶1"},{"name":"蝴蝶2-1","bone":"bone4","attachment":"蝴蝶2-1"},{"name":"蝴蝶8","bone":"bone16","attachment":"蝴蝶1"},{"name":"蝴蝶3","bone":"蝴蝶3","attachment":"蝴蝶2"},{"name":"蝴蝶7","bone":"bone14","attachment":"蝴蝶1"},{"name":"蝴蝶2","bone":"蝴蝶2","attachment":"蝴蝶2"},{"name":"蝴蝶1-2","bone":"bone3","attachment":"蝴蝶1-2"},{"name":"蝴蝶1-1","bone":"蝴蝶1","attachment":"蝴蝶1-1"},{"name":"蝴蝶1","bone":"bone2","attachment":"蝴蝶1"},{"name":"光圈","bone":"光圈","attachment":"光圈"},{"name":"图层 1","bone":"条幅","attachment":"图层 1"},{"name":"晋 副本","bone":"晋","attachment":"过2"},{"name":"晋 边框2","bone":"晋2","attachment":"过 边框"},{"name":"成 副本","bone":"成","attachment":"成"},{"name":"成 边框2","bone":"成2","attachment":"成 边框"},{"name":"升 副本","bone":"升","attachment":"关"},{"name":"升 边框2","bone":"升2","attachment":"关 边框"},{"name":"功 副本","bone":"功","attachment":"功"},{"name":"功 边框2","bone":"功2","attachment":"功 边框"},{"name":"白光","bone":"hit","attachment":"白光"}],"skins":{"default":{"huaban1":{"huaban1":{"x":0.03,"width":36,"height":36}},"huaban2":{"huaban1":{"x":0.03,"width":36,"height":36}},"huaban3":{"huaban1":{"x":0.03,"width":36,"height":36}},"huaban4":{"huaban1":{"x":0.03,"width":36,"height":36}},"huaban5":{"huaban1":{"x":0.03,"width":36,"height":36}},"huaban6":{"huaban1":{"x":0.03,"width":36,"height":36}},"huaban7":{"huaban1":{"x":0.03,"width":36,"height":36}},"huaban8":{"huaban1":{"x":0.03,"width":36,"height":36}},"huaban9":{"huaban1":{"x":0.03,"width":36,"height":36}},"光圈":{"光圈":{"width":560,"height":560}},"光束":{"光束":{"x":0.18,"width":51,"height":742}},"光束2":{"光束2":{"width":116,"height":841}},"光束3":{"光束":{"x":0.18,"width":51,"height":742}},"光束4":{"光束":{"x":0.18,"width":51,"height":742}},"光束5":{"光束2":{"width":116,"height":841}},"光束6":{"光束2":{"width":116,"height":841}},"光柱":{"光柱":{"scaleY":1.03,"width":532,"height":67}},"光柱2":{"光柱":{"width":532,"height":67}},"光柱3":{"光柱":{"width":532,"height":67}},"光柱4":{"光柱":{"width":532,"height":67}},"光柱5":{"光柱":{"scaleX":1.397,"width":532,"height":67}},"功 副本":{"功":{"width":99,"height":129}},"功 边框2":{"功 边框":{"width":99,"height":92}},"升 副本":{"关":{"width":99,"height":129}},"升 边框2":{"关 边框":{"width":93,"height":116}},"图层 1":{"图层 1":{"type":"mesh","uvs":[0.99949,0,0,0,0,1,0.99951,1,1,1,1,0],"triangles":[2,1,0,3,0,5,4,3,5,2,0,3],"vertices":[360.63,60.5,-361,60.5,-361,-60.5,360.65,-60.5,361,-60.5,361,60.5],"hull":6,"edges":[2,4,8,10,2,0,0,10,4,6,6,8,0,6],"width":722,"height":121}},"成 副本":{"成":{"width":99,"height":129}},"成 边框2":{"成 边框":{"width":93,"height":116}},"晋 副本":{"过":{"width":99,"height":129},"过2":{"path":"过","width":99,"height":129}},"晋 边框2":{"过 边框":{"width":113,"height":116}},"白光":{"白光":{"x":366.62,"y":620.84,"scaleX":7.744,"scaleY":7.584,"width":115,"height":205}},"蝴蝶1":{"蝴蝶1":{"type":"mesh","uvs":[1,0.99661,1,0,0,0,0,1],"triangles":[2,1,0,3,2,0],"vertices":[1,4,-8.46,21.36,1,1,4,7.78,-62.8,1,1,4,60.8,-52.57,1,1,4,44.51,31.87,1],"hull":4,"edges":[0,2,2,4,4,6,0,6],"width":54,"height":86}},"蝴蝶1-1":{"蝴蝶1-1":{"type":"mesh","uvs":[1,1,0,1,0,0,1,0],"triangles":[1,2,3,1,3,0],"vertices":[13.66,-5.18,-1.62,-9.92,-11.11,20.65,4.18,25.39],"hull":4,"edges":[0,2,2,4,4,6,0,6],"width":16,"height":32}},"蝴蝶1-10":{"蝴蝶1-2":{"type":"mesh","uvs":[1,0,1,1,0,1,0,0],"triangles":[2,3,0,2,0,1],"vertices":[1,29,26.09,-60.4,1,1,29,-10.6,10.7,1,1,29,32.95,33.17,1,1,29,69.63,-37.93,1],"hull":4,"edges":[0,2,2,4,4,6,0,6],"width":49,"height":80}},"蝴蝶1-2":{"蝴蝶1-2":{"type":"mesh","uvs":[1,0,1,1,0,1,0,0],"triangles":[2,3,0,2,0,1],"vertices":[1,5,26.09,-60.4,1,1,5,-10.6,10.7,1,1,5,32.95,33.17,1,1,5,69.63,-37.93,1],"hull":4,"edges":[0,2,2,4,4,6,0,6],"width":49,"height":80}},"蝴蝶1-3":{"蝴蝶1-1":{"type":"mesh","uvs":[1,1,0,1,0,0,1,0],"triangles":[1,2,3,1,3,0],"vertices":[13.66,-5.18,-1.62,-9.92,-11.11,20.65,4.18,25.39],"hull":4,"edges":[0,2,2,4,4,6,0,6],"width":16,"height":32}},"蝴蝶1-4":{"蝴蝶1-2":{"type":"mesh","uvs":[1,0,1,1,0,1,0,0],"triangles":[2,3,0,2,0,1],"vertices":[1,20,26.09,-60.4,1,1,20,-10.6,10.7,1,1,20,32.95,33.17,1,1,20,69.63,-37.93,1],"hull":4,"edges":[0,2,2,4,4,6,0,6],"width":49,"height":80}},"蝴蝶1-5":{"蝴蝶1-1":{"type":"mesh","uvs":[1,1,0,1,0,0,1,0],"triangles":[1,2,3,1,3,0],"vertices":[13.66,-5.18,-1.62,-9.92,-11.11,20.65,4.18,25.39],"hull":4,"edges":[0,2,2,4,4,6,0,6],"width":16,"height":32}},"蝴蝶1-6":{"蝴蝶1-2":{"type":"mesh","uvs":[1,0,1,1,0,1,0,0],"triangles":[2,3,0,2,0,1],"vertices":[1,23,26.09,-60.4,1,1,23,-10.6,10.7,1,1,23,32.95,33.17,1,1,23,69.63,-37.93,1],"hull":4,"edges":[0,2,2,4,4,6,0,6],"width":49,"height":80}},"蝴蝶1-7":{"蝴蝶1-1":{"type":"mesh","uvs":[1,1,0,1,0,0,1,0],"triangles":[1,2,3,1,3,0],"vertices":[13.66,-5.18,-1.62,-9.92,-11.11,20.65,4.18,25.39],"hull":4,"edges":[0,2,2,4,4,6,0,6],"width":16,"height":32}},"蝴蝶1-8":{"蝴蝶1-2":{"type":"mesh","uvs":[1,0,1,1,0,1,0,0],"triangles":[2,3,0,2,0,1],"vertices":[1,26,26.09,-60.4,1,1,26,-10.6,10.7,1,1,26,32.95,33.17,1,1,26,69.63,-37.93,1],"hull":4,"edges":[0,2,2,4,4,6,0,6],"width":49,"height":80}},"蝴蝶1-9":{"蝴蝶1-1":{"type":"mesh","uvs":[1,1,0,1,0,0,1,0],"triangles":[1,2,3,1,3,0],"vertices":[13.66,-5.18,-1.62,-9.92,-11.11,20.65,4.18,25.39],"hull":4,"edges":[0,2,2,4,4,6,0,6],"width":16,"height":32}},"蝴蝶10":{"蝴蝶1":{"type":"mesh","uvs":[1,0.99661,1,0,0,0,0,1],"triangles":[2,1,0,3,2,0],"vertices":[1,28,-8.46,21.36,1,1,28,7.78,-62.8,1,1,28,60.8,-52.57,1,1,28,44.51,31.87,1],"hull":4,"edges":[0,2,2,4,4,6,0,6],"width":54,"height":86}},"蝴蝶2":{"蝴蝶2":{"type":"mesh","uvs":[0,0,0,1,1,1,1,0],"triangles":[1,0,3,1,3,2],"vertices":[-3.61,16.54,-13.48,8.07,-1.11,-6.35,8.76,2.12],"hull":4,"edges":[0,2,2,4,4,6,0,6],"width":19,"height":13}},"蝴蝶2-1":{"蝴蝶2-1":{"type":"mesh","uvs":[0,0,0,1,1,1,1,0],"triangles":[1,0,3,1,3,2],"vertices":[22.52,43.68,-12.7,-9.76,14.86,-27.92,50.08,25.52],"hull":4,"edges":[0,2,2,4,4,6,0,6],"width":33,"height":64}},"蝴蝶2-10":{"蝴蝶2-2":{"type":"mesh","uvs":[0,0,0,1,1,1,1,0],"triangles":[1,0,3,1,3,2],"vertices":[30.81,35.42,-13.82,3.28,8.39,-27.56,53.02,4.59],"hull":4,"edges":[0,2,2,4,4,6,0,6],"width":38,"height":55}},"蝴蝶2-2":{"蝴蝶2-2":{"type":"mesh","uvs":[0,0,0,1,1,1,1,0],"triangles":[1,0,3,1,3,2],"vertices":[30.81,35.42,-13.82,3.28,8.39,-27.56,53.02,4.59],"hull":4,"edges":[0,2,2,4,4,6,0,6],"width":38,"height":55}},"蝴蝶2-3":{"蝴蝶2-1":{"type":"mesh","uvs":[0,0,0,1,1,1,1,0],"triangles":[1,0,3,1,3,2],"vertices":[22.52,43.68,-12.7,-9.76,14.86,-27.92,50.08,25.52],"hull":4,"edges":[0,2,2,4,4,6,0,6],"width":33,"height":64}},"蝴蝶2-4":{"蝴蝶2-2":{"type":"mesh","uvs":[0,0,0,1,1,1,1,0],"triangles":[1,0,3,1,3,2],"vertices":[30.81,35.42,-13.82,3.28,8.39,-27.56,53.02,4.59],"hull":4,"edges":[0,2,2,4,4,6,0,6],"width":38,"height":55}},"蝴蝶2-7":{"蝴蝶2-1":{"type":"mesh","uvs":[0,0,0,1,1,1,1,0],"triangles":[1,0,3,1,3,2],"vertices":[22.52,43.68,-12.7,-9.76,14.86,-27.92,50.08,25.52],"hull":4,"edges":[0,2,2,4,4,6,0,6],"width":33,"height":64}},"蝴蝶2-8":{"蝴蝶2-2":{"type":"mesh","uvs":[0,0,0,1,1,1,1,0],"triangles":[1,0,3,1,3,2],"vertices":[30.81,35.42,-13.82,3.28,8.39,-27.56,53.02,4.59],"hull":4,"edges":[0,2,2,4,4,6,0,6],"width":38,"height":55}},"蝴蝶2-9":{"蝴蝶2-1":{"type":"mesh","uvs":[0,0,0,1,1,1,1,0],"triangles":[1,0,3,1,3,2],"vertices":[22.52,43.68,-12.7,-9.76,14.86,-27.92,50.08,25.52],"hull":4,"edges":[0,2,2,4,4,6,0,6],"width":33,"height":64}},"蝴蝶3":{"蝴蝶2":{"type":"mesh","uvs":[0,0,0,1,1,1,1,0],"triangles":[1,0,3,1,3,2],"vertices":[-3.61,16.54,-13.48,8.07,-1.11,-6.35,8.76,2.12],"hull":4,"edges":[0,2,2,4,4,6,0,6],"width":19,"height":13}},"蝴蝶5":{"蝴蝶2":{"type":"mesh","uvs":[0,0,0,1,1,1,1,0],"triangles":[1,0,3,1,3,2],"vertices":[-3.61,16.54,-13.48,8.07,-1.11,-6.35,8.76,2.12],"hull":4,"edges":[0,2,2,4,4,6,0,6],"width":19,"height":13}},"蝴蝶6":{"蝴蝶2":{"type":"mesh","uvs":[0,0,0,1,1,1,1,0],"triangles":[1,0,3,1,3,2],"vertices":[-3.61,16.54,-13.48,8.07,-1.11,-6.35,8.76,2.12],"hull":4,"edges":[0,2,2,4,4,6,0,6],"width":19,"height":13}},"蝴蝶7":{"蝴蝶1":{"type":"mesh","uvs":[1,0.99661,1,0,0,0,0,1],"triangles":[2,1,0,3,2,0],"vertices":[1,19,-8.46,21.36,1,1,19,7.78,-62.8,1,1,19,60.8,-52.57,1,1,19,44.51,31.87,1],"hull":4,"edges":[0,2,2,4,4,6,0,6],"width":54,"height":86}},"蝴蝶8":{"蝴蝶1":{"type":"mesh","uvs":[1,0.99661,1,0,0,0,0,1],"triangles":[2,1,0,3,2,0],"vertices":[1,22,-8.46,21.36,1,1,22,7.78,-62.8,1,1,22,60.8,-52.57,1,1,22,44.51,31.87,1],"hull":4,"edges":[0,2,2,4,4,6,0,6],"width":54,"height":86}},"蝴蝶9":{"蝴蝶1":{"type":"mesh","uvs":[1,0.99661,1,0,0,0,0,1],"triangles":[2,1,0,3,2,0],"vertices":[1,25,-8.46,21.36,1,1,25,7.78,-62.8,1,1,25,60.8,-52.57,1,1,25,44.51,31.87,1],"hull":4,"edges":[0,2,2,4,4,6,0,6],"width":54,"height":86}},"闪光10":{"闪光":{"width":116,"height":115}},"闪光11":{"闪光":{"width":116,"height":115}},"闪光12":{"闪光":{"width":116,"height":115}},"闪光13":{"闪光":{"width":116,"height":115}},"闪光14":{"闪光":{"width":116,"height":115}},"闪光15":{"闪光":{"width":116,"height":115}},"闪光16":{"闪光":{"width":116,"height":115}},"闪光17":{"闪光":{"width":116,"height":115}},"闪光3":{"闪光":{"width":116,"height":115}},"闪光4":{"闪光":{"width":116,"height":115}},"闪光5":{"闪光":{"width":116,"height":115}},"闪光6":{"闪光":{"width":116,"height":115}},"闪光7":{"闪光":{"width":116,"height":115}},"闪光8":{"闪光":{"width":116,"height":115}},"闪光9":{"闪光":{"width":116,"height":115}}}},"animations":{"animation":{"slots":{"huaban1":{"color":[{"time":0.8333,"color":"ffffffff","curve":[0.25,0,0.75,1]},{"time":1.3333,"color":"ffffff00"}]},"huaban2":{"color":[{"time":1.3333,"color":"ffffffff","curve":[0.25,0,0.75,1]},{"time":1.8333,"color":"ffffff00"}]},"huaban3":{"color":[{"time":1.1667,"color":"ffffffff","curve":[0.25,0,0.75,1]},{"time":1.6667,"color":"ffffff00"}]},"huaban4":{"color":[{"time":1.5,"color":"ffffffff","curve":[0.25,0,0.75,1]},{"time":2,"color":"ffffff00"}]},"huaban5":{"color":[{"time":1,"color":"ffffffff","curve":[0.25,0,0.75,1]},{"time":1.5,"color":"ffffff00"}]},"huaban6":{"color":[{"time":1.6667,"color":"ffffffff","curve":[0.25,0,0.75,1]},{"time":2.1667,"color":"ffffff00"}]},"huaban7":{"color":[{"time":1.8333,"color":"ffffffff","curve":[0.25,0,0.75,1]},{"time":2.3333,"color":"ffffff00"}]},"huaban8":{"color":[{"time":2,"color":"ffffffff","curve":[0.25,0,0.75,1]},{"time":2.5,"color":"ffffff00"}]},"huaban9":{"color":[{"time":2.1667,"color":"ffffffff","curve":[0.25,0,0.75,1]},{"time":2.6667,"color":"ffffff00"}]},"光圈":{"color":[{"time":0,"color":"ffffff00","curve":"stepped"},{"time":0.6667,"color":"ffffff00","curve":[0.25,0,0.75,1]},{"time":0.7333,"color":"ffffffff","curve":"stepped"},{"time":0.9667,"color":"ffffffff","curve":[0.25,0,0.75,1]},{"time":1.3,"color":"ffffff00"}]},"光柱":{"color":[{"time":0,"color":"ffffff00","curve":"stepped"},{"time":0.1,"color":"ffffff00","curve":[0.25,0,0.75,1]},{"time":0.1333,"color":"ffffffff","curve":"stepped"},{"time":0.2,"color":"ffffffff","curve":[0.25,0,0.75,1]},{"time":0.2333,"color":"ffffff00"}]},"光柱2":{"color":[{"time":0,"color":"ffffff00","curve":"stepped"},{"time":0.2,"color":"ffffff00","curve":[0.25,0,0.75,1]},{"time":0.2333,"color":"ffffffff","curve":"stepped"},{"time":0.3,"color":"ffffffff","curve":[0.25,0,0.75,1]},{"time":0.3333,"color":"ffffff00"}],"attachment":[{"time":2.3,"name":"光柱"}]},"光柱3":{"color":[{"time":0,"color":"ffffff00","curve":"stepped"},{"time":0.2667,"color":"ffffff00","curve":[0.25,0,0.75,1]},{"time":0.3,"color":"ffffffff","curve":"stepped"},{"time":0.3667,"color":"ffffffff","curve":[0.25,0,0.75,1]},{"time":0.4,"color":"ffffff00"}]},"光柱4":{"color":[{"time":0,"color":"ffffff00","curve":"stepped"},{"time":0.3333,"color":"ffffff00","curve":[0.25,0,0.75,1]},{"time":0.3667,"color":"ffffffff","curve":"stepped"},{"time":0.4333,"color":"ffffffff","curve":[0.25,0,0.75,1]},{"time":0.4667,"color":"ffffff00"}]},"光柱5":{"color":[{"time":0,"color":"ffffff00","curve":"stepped"},{"time":0.4,"color":"ffffff00","curve":[0.25,0,0.75,1]},{"time":0.4333,"color":"ffffffff","curve":"stepped"},{"time":0.5,"color":"ffffffff","curve":[0.25,0,0.75,1]},{"time":0.5333,"color":"ffffff00"}]},"功 副本":{"color":[{"time":0,"color":"ffffff00","curve":"stepped"},{"time":2,"color":"ffffff00","curve":[0.25,0,0.75,1]},{"time":2.0333,"color":"ffffffff"}]},"功 边框2":{"color":[{"time":0,"color":"ffffff00","curve":"stepped"},{"time":2.1667,"color":"ffffff00","curve":[0.25,0,0.75,1]},{"time":2.2333,"color":"ffffffff","curve":[0.25,0,0.75,1]},{"time":2.6667,"color":"ffffff00"}]},"升 副本":{"color":[{"time":0,"color":"ffffff00","curve":"stepped"},{"time":2,"color":"ffffff00","curve":[0.25,0,0.75,1]},{"time":2.0333,"color":"ffffffff"}]},"升 边框2":{"color":[{"time":0,"color":"ffffff00","curve":"stepped"},{"time":2.1667,"color":"ffffff00","curve":[0.25,0,0.75,1]},{"time":2.2333,"color":"ffffffff","curve":[0.25,0,0.75,1]},{"time":2.6667,"color":"ffffff00"}]},"图层 1":{"color":[{"time":0,"color":"ffffff00","curve":"stepped"},{"time":1.6333,"color":"ffffff00","curve":[0.25,0,0.75,1]},{"time":1.6667,"color":"ffffffff"}]},"成 副本":{"color":[{"time":0,"color":"ffffff00","curve":"stepped"},{"time":2,"color":"ffffff00","curve":[0.25,0,0.75,1]},{"time":2.0333,"color":"ffffffff"}]},"成 边框2":{"color":[{"time":0,"color":"ffffff00","curve":"stepped"},{"time":2.1667,"color":"ffffff00","curve":[0.25,0,0.75,1]},{"time":2.2333,"color":"ffffffff","curve":[0.25,0,0.75,1]},{"time":2.6667,"color":"ffffff00"}]},"晋 副本":{"color":[{"time":0,"color":"ffffff00","curve":"stepped"},{"time":2,"color":"ffffff00","curve":[0.25,0,0.75,1]},{"time":2.0333,"color":"ffffffff"}]},"晋 边框2":{"color":[{"time":0,"color":"ffffff00","curve":"stepped"},{"time":2.1667,"color":"ffffff00","curve":[0.25,0,0.75,1]},{"time":2.2333,"color":"ffffffff","curve":[0.25,0,0.75,1]},{"time":2.6667,"color":"ffffff00"}]},"白光":{"color":[{"time":0,"color":"ffffff00","curve":"stepped"},{"time":0.6,"color":"ffffff00","curve":[0.25,0,0.75,1]},{"time":0.6667,"color":"ffffffff","curve":[0.25,0,0.75,1]},{"time":0.7667,"color":"ffffff00"}]},"蝴蝶1":{"color":[{"time":0,"color":"ffffff00","curve":"stepped"},{"time":0.9333,"color":"ffffff00","curve":[0.25,0,0.75,1]},{"time":1.1667,"color":"ffffffff","curve":"stepped"},{"time":1.8667,"color":"ffffffff","curve":[0.25,0,0.75,1]},{"time":2.2333,"color":"ffffff00"}]},"蝴蝶2":{"color":[{"time":0,"color":"ffffff00","curve":"stepped"},{"time":0.8333,"color":"ffffff00","curve":[0.25,0,0.75,1]},{"time":1.1,"color":"ffffffff","curve":[0.25,0,0.75,1]},{"time":2.1,"color":"ffffff00"}]},"蝴蝶3":{"color":[{"time":0,"color":"ffffff00","curve":"stepped"},{"time":0.8667,"color":"ffffff00","curve":[0.25,0,0.75,1]},{"time":0.9667,"color":"ffffffff","curve":"stepped"},{"time":1.8667,"color":"ffffffff","curve":[0.25,0,0.75,1]},{"time":2.1333,"color":"ffffff00"}]},"蝴蝶5":{"color":[{"time":0,"color":"ffffff00","curve":"stepped"},{"time":0.8,"color":"ffffff00","curve":[0.25,0,0.75,1]},{"time":0.9,"color":"ffffffff","curve":"stepped"},{"time":1.4667,"color":"ffffffff","curve":[0.25,0,0.75,1]},{"time":1.6333,"color":"ffffff00"}]},"蝴蝶6":{"color":[{"time":0,"color":"ffffff00","curve":"stepped"},{"time":0.7,"color":"ffffff00","curve":[0.25,0,0.75,1]},{"time":1.2667,"color":"ffffffff","curve":[0.25,0,0.75,1]},{"time":2.1333,"color":"ffffff00"}]},"蝴蝶7":{"color":[{"time":0,"color":"ffffff00","curve":"stepped"},{"time":1,"color":"ffffff00","curve":[0.25,0,0.75,1]},{"time":1.3333,"color":"ffffffff","curve":"stepped"},{"time":2,"color":"ffffffff","curve":[0.25,0,0.75,1]},{"time":2.4,"color":"ffffff00"}]},"蝴蝶8":{"color":[{"time":0,"color":"ffffff00","curve":"stepped"},{"time":0.8333,"color":"ffffff00","curve":[0.25,0,0.75,1]},{"time":1.0333,"color":"77f269ff","curve":"stepped"},{"time":2.1667,"color":"77f269ff","curve":[0.25,0,0.75,1]},{"time":2.3333,"color":"ffffff00"}]},"蝴蝶9":{"color":[{"time":0,"color":"ffffff00","curve":"stepped"},{"time":0.7333,"color":"ffffff00","curve":[0.25,0,0.75,1]},{"time":0.9,"color":"8d40cdff","curve":"stepped"},{"time":1.8333,"color":"8d40cdff","curve":[0.25,0,0.75,1]},{"time":2,"color":"ffffff00"}]},"蝴蝶10":{"color":[{"time":0,"color":"ffffff00","curve":"stepped"},{"time":0.7667,"color":"ffffff00","curve":[0.25,0,0.75,1]},{"time":1.1,"color":"ffffffff","curve":"stepped"},{"time":1.6,"color":"ffffffff","curve":[0.25,0,0.75,1]},{"time":2.2667,"color":"ffffff00"}]},"蝴蝶1-1":{"color":[{"time":0,"color":"ffffff00","curve":"stepped"},{"time":0.9333,"color":"ffffff00","curve":[0.25,0,0.75,1]},{"time":1.1667,"color":"ffffffff","curve":"stepped"},{"time":1.8667,"color":"ffffffff","curve":[0.25,0,0.75,1]},{"time":2.2333,"color":"ffffff00"}]},"蝴蝶1-2":{"color":[{"time":0,"color":"ffffff00","curve":"stepped"},{"time":0.9333,"color":"ffffff00","curve":[0.25,0,0.75,1]},{"time":1.1667,"color":"ffffffff","curve":"stepped"},{"time":1.8667,"color":"ffffffff","curve":[0.25,0,0.75,1]},{"time":2.2333,"color":"ffffff00"}]},"蝴蝶1-3":{"color":[{"time":0,"color":"ffffff00","curve":"stepped"},{"time":1,"color":"ffffff00","curve":[0.25,0,0.75,1]},{"time":1.3333,"color":"ffffffff","curve":"stepped"},{"time":2,"color":"ffffffff","curve":[0.25,0,0.75,1]},{"time":2.4,"color":"ffffff00"}]},"蝴蝶1-4":{"color":[{"time":0,"color":"ffffff00","curve":"stepped"},{"time":1,"color":"ffffff00","curve":[0.25,0,0.75,1]},{"time":1.3333,"color":"ffffffff","curve":"stepped"},{"time":2,"color":"ffffffff","curve":[0.25,0,0.75,1]},{"time":2.4,"color":"ffffff00"}]},"蝴蝶1-5":{"color":[{"time":0,"color":"ffffff00","curve":"stepped"},{"time":0.8333,"color":"ffffff00","curve":[0.25,0,0.75,1]},{"time":1.0333,"color":"77f269ff","curve":"stepped"},{"time":2.1667,"color":"77f269ff","curve":[0.25,0,0.75,1]},{"time":2.3333,"color":"ffffff00"}]},"蝴蝶1-6":{"color":[{"time":0,"color":"ffffff00","curve":"stepped"},{"time":0.8333,"color":"ffffff00","curve":[0.25,0,0.75,1]},{"time":1.0333,"color":"77f269ff","curve":"stepped"},{"time":2.1667,"color":"77f269ff","curve":[0.25,0,0.75,1]},{"time":2.3333,"color":"ffffff00"}]},"蝴蝶1-7":{"color":[{"time":0,"color":"ffffff00","curve":"stepped"},{"time":0.7333,"color":"ffffff00","curve":[0.25,0,0.75,1]},{"time":0.9,"color":"8d40cdff","curve":"stepped"},{"time":1.8333,"color":"8d40cdff","curve":[0.25,0,0.75,1]},{"time":2,"color":"ffffff00"}]},"蝴蝶1-8":{"color":[{"time":0,"color":"ffffff00","curve":"stepped"},{"time":0.7333,"color":"ffffff00","curve":[0.25,0,0.75,1]},{"time":0.9,"color":"8d40cdff","curve":"stepped"},{"time":1.8333,"color":"8d40cdff","curve":[0.25,0,0.75,1]},{"time":2,"color":"ffffff00"}]},"蝴蝶1-9":{"color":[{"time":0,"color":"ffffff00","curve":"stepped"},{"time":0.7667,"color":"ffffff00","curve":[0.25,0,0.75,1]},{"time":1.1,"color":"ffffffff","curve":"stepped"},{"time":1.6,"color":"ffffffff","curve":[0.25,0,0.75,1]},{"time":2.2667,"color":"ffffff00"}]},"蝴蝶1-10":{"color":[{"time":0,"color":"ffffff00","curve":"stepped"},{"time":0.7667,"color":"ffffff00","curve":[0.25,0,0.75,1]},{"time":1.1,"color":"ffffffff","curve":"stepped"},{"time":1.6,"color":"ffffffff","curve":[0.25,0,0.75,1]},{"time":2.2667,"color":"ffffff00"}]},"蝴蝶2-1":{"color":[{"time":0,"color":"ffffff00","curve":"stepped"},{"time":0.8333,"color":"ffffff00","curve":[0.25,0,0.75,1]},{"time":1.1,"color":"ffffffff","curve":[0.25,0,0.75,1]},{"time":2.1,"color":"ffffff00"}]},"蝴蝶2-2":{"color":[{"time":0,"color":"ffffff00","curve":"stepped"},{"time":0.8333,"color":"ffffff00","curve":[0.25,0,0.75,1]},{"time":1.1,"color":"ffffffff","curve":[0.25,0,0.75,1]},{"time":2.1,"color":"ffffff00"}]},"蝴蝶2-3":{"color":[{"time":0,"color":"ffffff00","curve":"stepped"},{"time":0.8667,"color":"ffffff00","curve":[0.25,0,0.75,1]},{"time":0.9667,"color":"ffffffff","curve":"stepped"},{"time":1.8667,"color":"ffffffff","curve":[0.25,0,0.75,1]},{"time":2.1333,"color":"ffffff00"}]},"蝴蝶2-4":{"color":[{"time":0,"color":"ffffff00","curve":"stepped"},{"time":0.8667,"color":"ffffff00","curve":[0.25,0,0.75,1]},{"time":0.9667,"color":"ffffffff","curve":"stepped"},{"time":1.8667,"color":"ffffffff","curve":[0.25,0,0.75,1]},{"time":2.1333,"color":"ffffff00"}]},"蝴蝶2-7":{"color":[{"time":0,"color":"ffffff00","curve":"stepped"},{"time":0.8,"color":"ffffff00","curve":[0.25,0,0.75,1]},{"time":0.9,"color":"ffffffff","curve":"stepped"},{"time":1.4667,"color":"ffffffff","curve":[0.25,0,0.75,1]},{"time":1.6333,"color":"ffffff00"}]},"蝴蝶2-8":{"color":[{"time":0,"color":"ffffff00","curve":"stepped"},{"time":0.8,"color":"ffffff00","curve":[0.25,0,0.75,1]},{"time":0.9,"color":"ffffffff","curve":"stepped"},{"time":1.4667,"color":"ffffffff","curve":[0.25,0,0.75,1]},{"time":1.6333,"color":"ffffff00"}]},"蝴蝶2-9":{"color":[{"time":0,"color":"ffffff00","curve":"stepped"},{"time":0.7,"color":"ffffff00","curve":[0.25,0,0.75,1]},{"time":1.2667,"color":"ffffffff","curve":[0.25,0,0.75,1]},{"time":2.1333,"color":"ffffff00"}]},"蝴蝶2-10":{"color":[{"time":0,"color":"ffffff00","curve":"stepped"},{"time":0.7,"color":"ffffff00","curve":[0.25,0,0.75,1]},{"time":1.2667,"color":"ffffffff","curve":[0.25,0,0.75,1]},{"time":2.1333,"color":"ffffff00"}]},"闪光3":{"color":[{"time":0,"color":"ffffff00","curve":"stepped"},{"time":1,"color":"ffffff00","curve":[0.25,0,0.75,1]},{"time":1.3333,"color":"ffffffff","curve":"stepped"},{"time":2.0667,"color":"ffffffff","curve":[0.25,0,0.75,1]},{"time":2.3333,"color":"ffffff00"}]},"闪光4":{"color":[{"time":0,"color":"ffffff00","curve":"stepped"},{"time":1.1667,"color":"ffffff00","curve":[0.25,0,0.75,1]},{"time":1.5,"color":"ffffffff","curve":"stepped"},{"time":2.0667,"color":"ffffffff","curve":[0.25,0,0.75,1]},{"time":2.4333,"color":"ffffff00"}]},"闪光5":{"color":[{"time":0,"color":"ffffff00","curve":"stepped"},{"time":1.3333,"color":"ffffff00","curve":[0.25,0,0.75,1]},{"time":1.6667,"color":"ffffffff","curve":"stepped"},{"time":2.0333,"color":"ffffffff","curve":[0.25,0,0.75,1]},{"time":2.3667,"color":"ffffff00"}]},"闪光6":{"color":[{"time":0,"color":"ffffff00","curve":"stepped"},{"time":1,"color":"ffffff00","curve":[0.25,0,0.75,1]},{"time":1.3333,"color":"ffffffff","curve":"stepped"},{"time":2,"color":"ffffffff","curve":[0.25,0,0.75,1]},{"time":2.2333,"color":"ffffff00"}]},"闪光7":{"color":[{"time":0,"color":"ffffff00","curve":"stepped"},{"time":1.3333,"color":"ffffff00","curve":[0.25,0,0.75,1]},{"time":1.6667,"color":"ffffffff","curve":"stepped"},{"time":2.1333,"color":"ffffffff","curve":[0.25,0,0.75,1]},{"time":2.3,"color":"ffffff00"}]},"闪光8":{"color":[{"time":0,"color":"ffffff00","curve":"stepped"},{"time":1,"color":"ffffff00","curve":[0.25,0,0.75,1]},{"time":1.3333,"color":"ffffffff","curve":"stepped"},{"time":2.5667,"color":"ffffffff","curve":[0.25,0,0.75,1]},{"time":2.7333,"color":"ffffff00"}]},"闪光9":{"color":[{"time":0,"color":"ffffff00","curve":"stepped"},{"time":1,"color":"ffffff00","curve":[0.25,0,0.75,1]},{"time":1.3333,"color":"ffffffff","curve":"stepped"},{"time":2.4,"color":"ffffffff","curve":[0.25,0,0.75,1]},{"time":2.5667,"color":"ffffff00"}]},"闪光10":{"color":[{"time":0,"color":"ffffff00","curve":"stepped"},{"time":1.3667,"color":"ffffff00","curve":[0.25,0,0.75,1]},{"time":1.7,"color":"ffffffff","curve":"stepped"},{"time":2.2667,"color":"ffffffff","curve":[0.25,0,0.75,1]},{"time":2.4333,"color":"ffffff00"}]},"闪光11":{"color":[{"time":0,"color":"ffffff00","curve":"stepped"},{"time":1,"color":"ffffff00","curve":[0.25,0,0.75,1]},{"time":1.3333,"color":"ffffffff","curve":"stepped"},{"time":1.8333,"color":"ffffffff","curve":[0.25,0,0.75,1]},{"time":2,"color":"ffffff00"}]},"闪光12":{"color":[{"time":0,"color":"ffffff00","curve":"stepped"},{"time":1.5,"color":"ffffff00","curve":[0.25,0,0.75,1]},{"time":1.8333,"color":"ffffffff","curve":"stepped"},{"time":2.3,"color":"ffffffff","curve":[0.25,0,0.75,1]},{"time":2.4667,"color":"ffffff00"}]},"闪光13":{"color":[{"time":0,"color":"ffffff00","curve":"stepped"},{"time":1.1667,"color":"ffffff00","curve":[0.25,0,0.75,1]},{"time":1.5,"color":"ffffffff","curve":"stepped"},{"time":2.0333,"color":"ffffffff","curve":[0.25,0,0.75,1]},{"time":2.2,"color":"ffffff00"}]},"闪光14":{"color":[{"time":0,"color":"ffffff00","curve":"stepped"},{"time":1.3333,"color":"ffffff00","curve":[0.25,0,0.75,1]},{"time":1.6667,"color":"ffffffff","curve":"stepped"},{"time":2.6,"color":"ffffffff","curve":[0.25,0,0.75,1]},{"time":2.7667,"color":"ffffff00"}]},"闪光15":{"color":[{"time":0,"color":"ffffff00","curve":"stepped"},{"time":1.1333,"color":"ffffff00","curve":[0.25,0,0.75,1]},{"time":1.5667,"color":"ffffffff","curve":"stepped"},{"time":2.3333,"color":"ffffffff","curve":[0.25,0,0.75,1]},{"time":2.7333,"color":"ffffff00"}]},"闪光16":{"color":[{"time":0,"color":"ffffff00","curve":"stepped"},{"time":1.2,"color":"ffffff00","curve":[0.25,0,0.75,1]},{"time":1.5667,"color":"ffffffff","curve":"stepped"},{"time":2.2667,"color":"ffffffff","curve":[0.25,0,0.75,1]},{"time":2.4333,"color":"ffffff00"}]},"闪光17":{"color":[{"time":0,"color":"ffffff00","curve":"stepped"},{"time":1.1,"color":"ffffff00","curve":[0.25,0,0.75,1]},{"time":1.5333,"color":"ffffffff","curve":"stepped"},{"time":2.5,"color":"ffffffff","curve":[0.25,0,0.75,1]},{"time":2.6667,"color":"ffffff00"}]}},"bones":{"光束":{"translate":[{"time":0,"x":-54.06,"y":-1240.89,"curve":"stepped"},{"time":0.1,"x":-54.06,"y":-1240.89,"curve":[0.25,0,0.75,1]},{"time":0.3,"x":-54.06,"y":893.84}]},"光束2":{"translate":[{"time":0,"x":-41.18,"y":-1249.31,"curve":"stepped"},{"time":0.1333,"x":-41.18,"y":-1249.31,"curve":[0.25,0,0.75,1]},{"time":0.4,"x":-41.18,"y":955.44}]},"光束3":{"translate":[{"time":0,"x":93.57,"y":-1380.63,"curve":"stepped"},{"time":0.2,"x":93.57,"y":-1380.63,"curve":[0.25,0,0.75,1]},{"time":0.5333,"x":93.57,"y":1046.18}],"scale":[{"time":0,"x":1.793,"y":1.35}],"shear":[{"time":0,"x":0,"y":0}]},"光束4":{"translate":[{"time":0,"x":-121.06,"y":-1317.12,"curve":"stepped"},{"time":0.3333,"x":-121.06,"y":-1317.12,"curve":[0.25,0,0.75,1]},{"time":0.5667,"x":-121.06,"y":993.52}],"scale":[{"time":0,"x":3.289,"y":1.219}]},"光束6":{"translate":[{"time":0,"x":207.05,"y":-1313.52,"curve":"stepped"},{"time":0.3667,"x":207.05,"y":-1313.52,"curve":[0.25,0,0.75,1]},{"time":0.5333,"x":207.05,"y":992.42}],"scale":[{"time":0,"x":0.97,"y":1.12}]},"光束5":{"translate":[{"time":0,"x":-64.87,"y":-1435.35,"curve":"stepped"},{"time":0.4667,"x":-64.87,"y":-1435.35,"curve":[0.25,0,0.75,1]},{"time":0.6667,"x":-64.87,"y":1095.23}],"scale":[{"time":0,"x":1.735,"y":1.551}]},"光柱":{"translate":[{"time":0,"x":-130.28,"y":0}],"scale":[{"time":0,"x":1,"y":1.03}]},"光柱2":{"translate":[{"time":0,"x":-370.12,"y":0}]},"光柱3":{"translate":[{"time":0,"x":357,"y":0}]},"光柱4":{"translate":[{"time":0,"x":-690.78,"y":0}]},"光柱5":{"translate":[{"time":0,"x":782.18,"y":0}]},"花瓣":{"translate":[{"time":0,"x":3.66,"y":3.66},{"time":1.3333,"x":-57.04,"y":-1397.18}]},"花瓣5":{"translate":[{"time":0,"x":3.66,"y":3.66,"curve":"stepped"},{"time":0.1667,"x":3.66,"y":3.66},{"time":1.5,"x":57.04,"y":-1397.18}]},"花瓣3":{"translate":[{"time":0,"x":3.66,"y":3.66,"curve":"stepped"},{"time":0.3333,"x":3.66,"y":3.66},{"time":1.6667,"x":99.82,"y":-1394.12}]},"花瓣2":{"translate":[{"time":0,"x":3.66,"y":3.66,"curve":"stepped"},{"time":0.5,"x":3.66,"y":3.66},{"time":1.8333,"x":68.45,"y":-1397.18}]},"花瓣4":{"translate":[{"time":0,"x":3.66,"y":3.66,"curve":"stepped"},{"time":0.6667,"x":3.66,"y":3.66},{"time":2,"x":-51.34,"y":-1397.18}]},"花瓣6":{"translate":[{"time":0,"x":3.66,"y":3.66,"curve":"stepped"},{"time":0.8333,"x":3.66,"y":3.66},{"time":2.1667,"x":77,"y":-1396.23}]},"花瓣7":{"translate":[{"time":0,"x":3.66,"y":3.66,"curve":"stepped"},{"time":1,"x":3.66,"y":3.66},{"time":2.3333,"x":-68.45,"y":-1393.39}]},"光圈":{"scale":[{"time":0.6667,"x":0.2,"y":0.2,"curve":[0,0.41,0.622,1]},{"time":1.2667,"x":2.2,"y":2.2}]},"条幅":{"scale":[{"time":1.6667,"x":1,"y":1,"curve":[0.25,0,0.75,1]},{"time":1.9333,"x":1,"y":1.2,"curve":[0.25,0,0.75,1]},{"time":2,"x":1,"y":1}]},"晋":{"scale":[{"time":2,"x":1,"y":1,"curve":[0.25,0,0.75,1]},{"time":2.0333,"x":1.5,"y":1.5,"curve":[0.25,0,0.75,1]},{"time":2.2,"x":1,"y":1}]},"升":{"scale":[{"time":2,"x":1,"y":1,"curve":[0.25,0,0.75,1]},{"time":2.0333,"x":1.5,"y":1.5,"curve":[0.25,0,0.75,1]},{"time":2.2,"x":1,"y":1}]},"成":{"translate":[{"time":2.2333,"x":0,"y":-0.2}],"scale":[{"time":2,"x":1,"y":1,"curve":[0.25,0,0.75,1]},{"time":2.0333,"x":1.5,"y":1.5,"curve":[0.25,0,0.75,1]},{"time":2.2,"x":1,"y":1}]},"功":{"scale":[{"time":2,"x":1,"y":1,"curve":[0.25,0,0.75,1]},{"time":2.0333,"x":1.5,"y":1.5,"curve":[0.25,0,0.75,1]},{"time":2.2,"x":1,"y":1}]},"root":{"translate":[{"time":0,"x":0,"y":0,"curve":"stepped"},{"time":3,"x":0,"y":0}]},"花瓣8":{"translate":[{"time":0,"x":3.66,"y":3.66,"curve":"stepped"},{"time":1.1667,"x":3.66,"y":3.66},{"time":2.5,"x":-34.36,"y":-1393.39}]},"花瓣9":{"translate":[{"time":0,"x":3.66,"y":3.66,"curve":"stepped"},{"time":1.3333,"x":3.66,"y":3.66},{"time":2.6667,"x":-24.13,"y":-1393.39}]},"功2":{"scale":[{"time":2.2,"x":1,"y":1,"curve":[0.25,0,0.75,1]},{"time":2.6667,"x":1.5,"y":1.5}]},"升2":{"scale":[{"time":2.2,"x":1,"y":1,"curve":[0.25,0,0.75,1]},{"time":2.6667,"x":1.5,"y":1.5}]},"成2":{"scale":[{"time":2.2,"x":1,"y":1,"curve":[0.25,0,0.75,1]},{"time":2.6667,"x":1.5,"y":1.5}]},"晋2":{"scale":[{"time":2.2,"x":1,"y":1,"curve":[0.25,0,0.75,1]},{"time":2.6667,"x":1.7,"y":1.7}]},"蝴蝶群":{"translate":[{"time":0,"x":357.02,"y":699.07}]},"bone14":{"shear":[{"time":0,"x":0,"y":0,"curve":"stepped"},{"time":1,"x":0,"y":0,"curve":[0.25,0,0.75,1]},{"time":1.1,"x":40,"y":0,"curve":[0.25,0,0.75,1]},{"time":1.2,"x":120,"y":0,"curve":[0.25,0,0.75,1]},{"time":1.3,"x":40.37,"y":0,"curve":[0.25,0,0.75,1]},{"time":1.4,"x":0,"y":0,"curve":[0.25,0,0.75,1]},{"time":1.5,"x":40,"y":0,"curve":[0.25,0,0.75,1]},{"time":1.6,"x":120,"y":0,"curve":[0.25,0,0.75,1]},{"time":1.7,"x":40.37,"y":0,"curve":[0.25,0,0.75,1]},{"time":1.8,"x":0,"y":0,"curve":[0.25,0,0.75,1]},{"time":1.9,"x":40,"y":0,"curve":[0.25,0,0.75,1]},{"time":2,"x":120,"y":0,"curve":[0.25,0,0.75,1]},{"time":2.1,"x":40.37,"y":0,"curve":[0.25,0,0.75,1]},{"time":2.2,"x":0,"y":0,"curve":[0.25,0,0.75,1]},{"time":2.3,"x":40,"y":0,"curve":[0.25,0,0.75,1]},{"time":2.4,"x":120,"y":0,"curve":[0.25,0,0.75,1]},{"time":2.5,"x":40.37,"y":0,"curve":[0.25,0,0.75,1]},{"time":2.6,"x":0,"y":0}]},"bone13":{"shear":[{"time":0,"x":0,"y":0,"curve":"stepped"},{"time":0.7667,"x":0,"y":0,"curve":[0.25,0,0.75,1]},{"time":0.8667,"x":40,"y":0,"curve":[0.25,0,0.75,1]},{"time":0.9667,"x":120,"y":0,"curve":[0.25,0,0.75,1]},{"time":1.0667,"x":40,"y":0,"curve":[0.25,0,0.75,1]},{"time":1.1667,"x":0,"y":0,"curve":[0.25,0,0.75,1]},{"time":1.2667,"x":40,"y":0,"curve":[0.25,0,0.75,1]},{"time":1.3667,"x":120,"y":0,"curve":[0.25,0,0.75,1]},{"time":1.4667,"x":40,"y":0,"curve":[0.25,0,0.75,1]},{"time":1.5667,"x":0,"y":0,"curve":[0.25,0,0.75,1]},{"time":1.6667,"x":40,"y":0,"curve":[0.25,0,0.75,1]},{"time":1.7667,"x":120,"y":0,"curve":[0.25,0,0.75,1]},{"time":1.8667,"x":40,"y":0,"curve":[0.25,0,0.75,1]},{"time":1.9667,"x":0,"y":0,"curve":[0.25,0,0.75,1]},{"time":2.0667,"x":40,"y":0,"curve":[0.25,0,0.75,1]},{"time":2.1667,"x":120,"y":0,"curve":[0.25,0,0.75,1]},{"time":2.2667,"x":40,"y":0,"curve":[0.25,0,0.75,1]},{"time":2.3667,"x":0,"y":0}]},"bone17":{"shear":[{"time":0,"x":0,"y":0,"curve":"stepped"},{"time":0.8667,"x":0,"y":0,"curve":[0.25,0,0.75,1]},{"time":0.9667,"x":-40,"y":0,"curve":[0.25,0,0.75,1]},{"time":1.0667,"x":-120,"y":0,"curve":[0.25,0,0.75,1]},{"time":1.1667,"x":-40,"y":0,"curve":[0.25,0,0.75,1]},{"time":1.2667,"x":0,"y":0,"curve":[0.25,0,0.75,1]},{"time":1.3667,"x":-40,"y":0,"curve":[0.25,0,0.75,1]},{"time":1.4667,"x":-120,"y":0,"curve":[0.25,0,0.75,1]},{"time":1.5667,"x":-40,"y":0,"curve":[0.25,0,0.75,1]},{"time":1.6667,"x":0,"y":0,"curve":[0.25,0,0.75,1]},{"time":1.7667,"x":-40,"y":0,"curve":[0.25,0,0.75,1]},{"time":1.8667,"x":-120,"y":0,"curve":[0.25,0,0.75,1]},{"time":1.9667,"x":-40,"y":0,"curve":[0.25,0,0.75,1]},{"time":2.0667,"x":0,"y":0,"curve":[0.25,0,0.75,1]},{"time":2.1667,"x":-40,"y":0,"curve":[0.25,0,0.75,1]},{"time":2.2667,"x":-120,"y":0,"curve":[0.25,0,0.75,1]},{"time":2.3667,"x":-40,"y":0,"curve":[0.25,0,0.75,1]},{"time":2.4667,"x":0,"y":0,"curve":[0.25,0,0.75,1]},{"time":2.5667,"x":-40,"y":0,"curve":[0.25,0,0.75,1]},{"time":2.6667,"x":-120,"y":0}]},"bone21":{"shear":[{"time":0,"x":0,"y":0,"curve":"stepped"},{"time":0.6333,"x":0,"y":0,"curve":[0.25,0,0.75,1]},{"time":0.7333,"x":-40,"y":0,"curve":[0.25,0,0.75,1]},{"time":0.8333,"x":-120,"y":0,"curve":[0.25,0,0.75,1]},{"time":0.9333,"x":-40,"y":0,"curve":[0.25,0,0.75,1]},{"time":1.0333,"x":0,"y":0,"curve":[0.25,0,0.75,1]},{"time":1.1333,"x":-40,"y":0,"curve":[0.25,0,0.75,1]},{"time":1.2333,"x":-120,"y":0,"curve":[0.25,0,0.75,1]},{"time":1.3333,"x":-40,"y":0,"curve":[0.25,0,0.75,1]},{"time":1.4333,"x":0,"y":0,"curve":[0.25,0,0.75,1]},{"time":1.5333,"x":-40,"y":0,"curve":[0.25,0,0.75,1]},{"time":1.6333,"x":-120,"y":0,"curve":[0.25,0,0.75,1]},{"time":1.7333,"x":-40,"y":0,"curve":[0.25,0,0.75,1]},{"time":1.8333,"x":0,"y":0,"curve":[0.25,0,0.75,1]},{"time":1.9333,"x":-40,"y":0,"curve":[0.25,0,0.75,1]},{"time":2.0333,"x":-120,"y":0,"curve":[0.25,0,0.75,1]},{"time":2.1333,"x":-40,"y":0,"curve":[0.25,0,0.75,1]},{"time":2.2333,"x":0,"y":0,"curve":[0.25,0,0.75,1]},{"time":2.3333,"x":-40,"y":0,"curve":[0.25,0,0.75,1]},{"time":2.4333,"x":-120,"y":0,"curve":[0.25,0,0.75,1]},{"time":2.5333,"x":-40,"y":0,"curve":[0.25,0,0.75,1]},{"time":2.6333,"x":0,"y":0}]},"bone2":{"shear":[{"time":0,"x":40,"y":0,"curve":"stepped"},{"time":0.9333,"x":40,"y":0,"curve":[0.25,0,0.75,1]},{"time":1.0333,"x":120,"y":0,"curve":[0.25,0,0.75,1]},{"time":1.1333,"x":40.37,"y":0,"curve":[0.25,0,0.75,1]},{"time":1.2333,"x":0,"y":0,"curve":[0.25,0,0.75,1]},{"time":1.3333,"x":40,"y":0,"curve":[0.25,0,0.75,1]},{"time":1.4333,"x":120,"y":0,"curve":[0.25,0,0.75,1]},{"time":1.5333,"x":40.37,"y":0,"curve":[0.25,0,0.75,1]},{"time":1.6333,"x":0,"y":0,"curve":[0.25,0,0.75,1]},{"time":1.7333,"x":40,"y":0,"curve":[0.25,0,0.75,1]},{"time":1.8333,"x":120,"y":0,"curve":[0.25,0,0.75,1]},{"time":1.9333,"x":40.37,"y":0,"curve":[0.25,0,0.75,1]},{"time":2.0333,"x":0,"y":0,"curve":[0.25,0,0.75,1]},{"time":2.1333,"x":40,"y":0,"curve":[0.25,0,0.75,1]},{"time":2.2333,"x":120,"y":0}]},"蝴蝶6":{"rotate":[{"time":0,"angle":-98.92,"curve":"stepped"},{"time":0.7667,"angle":-98.92}],"translate":[{"time":0,"x":-110.76,"y":67.89,"curve":"stepped"},{"time":0.6333,"x":-110.76,"y":67.89,"curve":[0.25,0,0.75,1]},{"time":1.9333,"x":11.86,"y":136.91}],"shear":[{"time":0,"x":-180,"y":0,"curve":"stepped"},{"time":0.7667,"x":-180,"y":0}]},"蝴蝶10":{"rotate":[{"time":0,"angle":-30.36,"curve":"stepped"},{"time":0.7667,"angle":-30.36}],"translate":[{"time":0,"x":-16.46,"y":27.96,"curve":"stepped"},{"time":0.6667,"x":-16.46,"y":27.96,"curve":[0.25,0,0.75,1]},{"time":1.9333,"x":42.77,"y":225.99}],"scale":[{"time":0,"x":0.65,"y":0.65,"curve":"stepped"},{"time":0.7667,"x":0.65,"y":0.65}]},"蝴蝶8":{"rotate":[{"time":0,"angle":72.11,"curve":"stepped"},{"time":0.9333,"angle":72.11}],"translate":[{"time":0,"x":8.81,"y":65.65,"curve":"stepped"},{"time":0.8667,"x":8.81,"y":65.65,"curve":[0.25,0,0.75,1]},{"time":2.4333,"x":-29.07,"y":207.18}],"scale":[{"time":0,"x":0.6,"y":0.6,"curve":"stepped"},{"time":0.9333,"x":0.6,"y":0.6}],"shear":[{"time":0,"x":-180,"y":0,"curve":"stepped"},{"time":0.9333,"x":-180,"y":0}]},"bone3":{"shear":[{"time":0,"x":-40,"y":0,"curve":"stepped"},{"time":0.9333,"x":-40,"y":0,"curve":[0.25,0,0.75,1]},{"time":1.0333,"x":-120,"y":0,"curve":[0.25,0,0.75,1]},{"time":1.1333,"x":-40,"y":0,"curve":[0.25,0,0.75,1]},{"time":1.2333,"x":0,"y":0,"curve":[0.25,0,0.75,1]},{"time":1.3333,"x":-40,"y":0,"curve":[0.25,0,0.75,1]},{"time":1.4333,"x":-120,"y":0,"curve":[0.25,0,0.75,1]},{"time":1.5333,"x":-40,"y":0,"curve":[0.25,0,0.75,1]},{"time":1.6333,"x":0,"y":0,"curve":[0.25,0,0.75,1]},{"time":1.7333,"x":-40,"y":0,"curve":[0.25,0,0.75,1]},{"time":1.8333,"x":-120,"y":0,"curve":[0.25,0,0.75,1]},{"time":1.9333,"x":-40,"y":0,"curve":[0.25,0,0.75,1]},{"time":2.0333,"x":0,"y":0,"curve":[0.25,0,0.75,1]},{"time":2.1333,"x":-40,"y":0,"curve":[0.25,0,0.75,1]},{"time":2.2333,"x":-120,"y":0}]},"bone15":{"shear":[{"time":0,"x":0,"y":0,"curve":"stepped"},{"time":1,"x":0,"y":0,"curve":[0.25,0,0.75,1]},{"time":1.1,"x":-40,"y":0,"curve":[0.25,0,0.75,1]},{"time":1.2,"x":-120,"y":0,"curve":[0.25,0,0.75,1]},{"time":1.3,"x":-40,"y":0,"curve":[0.25,0,0.75,1]},{"time":1.4,"x":0,"y":0,"curve":[0.25,0,0.75,1]},{"time":1.5,"x":-40,"y":0,"curve":[0.25,0,0.75,1]},{"time":1.6,"x":-120,"y":0,"curve":[0.25,0,0.75,1]},{"time":1.7,"x":-40,"y":0,"curve":[0.25,0,0.75,1]},{"time":1.8,"x":0,"y":0,"curve":[0.25,0,0.75,1]},{"time":1.9,"x":-40,"y":0,"curve":[0.25,0,0.75,1]},{"time":2,"x":-120,"y":0,"curve":[0.25,0,0.75,1]},{"time":2.1,"x":-40,"y":0,"curve":[0.25,0,0.75,1]},{"time":2.2,"x":0,"y":0,"curve":[0.25,0,0.75,1]},{"time":2.3,"x":-40,"y":0,"curve":[0.25,0,0.75,1]},{"time":2.4,"x":-120,"y":0,"curve":[0.25,0,0.75,1]},{"time":2.5,"x":-40,"y":0,"curve":[0.25,0,0.75,1]},{"time":2.6,"x":0,"y":0}]},"bone4":{"shear":[{"time":0,"x":0,"y":0,"curve":"stepped"},{"time":0.7667,"x":0,"y":0,"curve":[0.25,0,0.75,1]},{"time":0.8667,"x":-40,"y":0,"curve":[0.25,0,0.75,1]},{"time":0.9667,"x":-120,"y":0,"curve":[0.25,0,0.75,1]},{"time":1.0667,"x":-40,"y":0,"curve":[0.25,0,0.75,1]},{"time":1.1667,"x":0,"y":0,"curve":[0.25,0,0.75,1]},{"time":1.2667,"x":-40,"y":0,"curve":[0.25,0,0.75,1]},{"time":1.3667,"x":-120,"y":0,"curve":[0.25,0,0.75,1]},{"time":1.4667,"x":-40,"y":0,"curve":[0.25,0,0.75,1]},{"time":1.5667,"x":0,"y":0,"curve":[0.25,0,0.75,1]},{"time":1.6667,"x":-40,"y":0,"curve":[0.25,0,0.75,1]},{"time":1.7667,"x":-120,"y":0,"curve":[0.25,0,0.75,1]},{"time":1.8667,"x":-40,"y":0,"curve":[0.25,0,0.75,1]},{"time":1.9667,"x":0,"y":0,"curve":[0.25,0,0.75,1]},{"time":2.0667,"x":-40,"y":0,"curve":[0.25,0,0.75,1]},{"time":2.1667,"x":-120,"y":0,"curve":[0.25,0,0.75,1]},{"time":2.2667,"x":-40,"y":0,"curve":[0.25,0,0.75,1]},{"time":2.3667,"x":0,"y":0}]},"bone11":{"shear":[{"time":0,"x":0,"y":0,"curve":"stepped"},{"time":0.8,"x":0,"y":0,"curve":[0.25,0,0.75,1]},{"time":0.9,"x":40,"y":0,"curve":[0.25,0,0.75,1]},{"time":1,"x":120,"y":0,"curve":[0.25,0,0.75,1]},{"time":1.1,"x":40,"y":0,"curve":[0.25,0,0.75,1]},{"time":1.2,"x":0,"y":0,"curve":[0.25,0,0.75,1]},{"time":1.3,"x":40,"y":0,"curve":[0.25,0,0.75,1]},{"time":1.4,"x":120,"y":0,"curve":[0.25,0,0.75,1]},{"time":1.5,"x":40,"y":0,"curve":[0.25,0,0.75,1]},{"time":1.6,"x":0,"y":0,"curve":[0.25,0,0.75,1]},{"time":1.7,"x":40,"y":0,"curve":[0.25,0,0.75,1]},{"time":1.8,"x":120,"y":0,"curve":[0.25,0,0.75,1]},{"time":1.9,"x":40,"y":0,"curve":[0.25,0,0.75,1]},{"time":2,"x":0,"y":0,"curve":[0.25,0,0.75,1]},{"time":2.1,"x":40,"y":0,"curve":[0.25,0,0.75,1]},{"time":2.2,"x":120,"y":0,"curve":[0.25,0,0.75,1]},{"time":2.3,"x":40,"y":0,"curve":[0.25,0,0.75,1]},{"time":2.4,"x":0,"y":0}]},"蝴蝶7":{"rotate":[{"time":0,"angle":-33.77,"curve":"stepped"},{"time":1,"angle":-33.77}],"translate":[{"time":0,"x":119.93,"y":-40.92,"curve":"stepped"},{"time":1,"x":119.93,"y":-40.92,"curve":[0.25,0,0.75,1]},{"time":2.1667,"x":238.17,"y":-170.72}],"scale":[{"time":0,"x":0.7,"y":0.7,"curve":"stepped"},{"time":1,"x":0.7,"y":0.7}]},"蝴蝶5":{"rotate":[{"time":0,"angle":9.58,"curve":"stepped"},{"time":0.8,"angle":9.58}],"translate":[{"time":0,"x":-215.64,"y":29.13,"curve":"stepped"},{"time":0.7667,"x":-215.64,"y":29.13,"curve":[0.25,0,0.75,1]},{"time":1.7333,"x":-426.81,"y":200.61}]},"蝴蝶9":{"rotate":[{"time":0,"angle":-11.32}],"translate":[{"time":0,"x":-56.14,"y":-12.67,"curve":[0.25,0,0.75,1]},{"time":2.0667,"x":-256.46,"y":-56.47}],"scale":[{"time":0,"x":0.8,"y":0.8,"curve":[0.25,0,0.75,1]},{"time":2,"x":0.6,"y":0.6}],"shear":[{"time":0,"x":0,"y":0}]},"bone18":{"shear":[{"time":0,"x":0,"y":0,"curve":[0.25,0,0.75,1]},{"time":0.7333,"x":120,"y":0,"curve":[0.25,0,0.75,1]},{"time":0.8333,"x":40.37,"y":0,"curve":[0.25,0,0.75,1]},{"time":0.9333,"x":0,"y":0,"curve":[0.25,0,0.75,1]},{"time":1.0333,"x":40,"y":0,"curve":[0.25,0,0.75,1]},{"time":1.1333,"x":120,"y":0,"curve":[0.25,0,0.75,1]},{"time":1.2333,"x":40.37,"y":0,"curve":[0.25,0,0.75,1]},{"time":1.3333,"x":0,"y":0,"curve":[0.25,0,0.75,1]},{"time":1.4333,"x":40,"y":0,"curve":[0.25,0,0.75,1]},{"time":1.5333,"x":120,"y":0,"curve":[0.25,0,0.75,1]},{"time":1.6333,"x":40.37,"y":0,"curve":[0.25,0,0.75,1]},{"time":1.7333,"x":0,"y":0,"curve":[0.25,0,0.75,1]},{"time":1.8333,"x":40,"y":0,"curve":[0.25,0,0.75,1]},{"time":1.9333,"x":120,"y":0,"curve":[0.25,0,0.75,1]},{"time":2.0333,"x":40.37,"y":0,"curve":[0.25,0,0.75,1]},{"time":2.1333,"x":0,"y":0,"curve":[0.25,0,0.75,1]},{"time":2.2333,"x":40,"y":0,"curve":[0.25,0,0.75,1]},{"time":2.3333,"x":120,"y":0,"curve":[0.25,0,0.75,1]},{"time":2.4333,"x":40.37,"y":0,"curve":[0.25,0,0.75,1]},{"time":2.5333,"x":0,"y":0,"curve":[0.25,0,0.75,1]},{"time":2.6333,"x":40,"y":0}]},"bone5":{"shear":[{"time":0,"x":0,"y":0,"curve":"stepped"},{"time":0.7667,"x":0,"y":0,"curve":[0.25,0,0.75,1]},{"time":0.8667,"x":40,"y":0,"curve":[0.25,0,0.75,1]},{"time":0.9667,"x":120,"y":0,"curve":[0.25,0,0.75,1]},{"time":1.0667,"x":40,"y":0,"curve":[0.25,0,0.75,1]},{"time":1.1667,"x":0,"y":0,"curve":[0.25,0,0.75,1]},{"time":1.2667,"x":40,"y":0,"curve":[0.25,0,0.75,1]},{"time":1.3667,"x":120,"y":0,"curve":[0.25,0,0.75,1]},{"time":1.4667,"x":40,"y":0,"curve":[0.25,0,0.75,1]},{"time":1.5667,"x":0,"y":0,"curve":[0.25,0,0.75,1]},{"time":1.6667,"x":40,"y":0,"curve":[0.25,0,0.75,1]},{"time":1.7667,"x":120,"y":0,"curve":[0.25,0,0.75,1]},{"time":1.8667,"x":40,"y":0,"curve":[0.25,0,0.75,1]},{"time":1.9667,"x":0,"y":0,"curve":[0.25,0,0.75,1]},{"time":2.0667,"x":40,"y":0,"curve":[0.25,0,0.75,1]},{"time":2.1667,"x":120,"y":0,"curve":[0.25,0,0.75,1]},{"time":2.2667,"x":40,"y":0,"curve":[0.25,0,0.75,1]},{"time":2.3667,"x":0,"y":0}]},"bone6":{"shear":[{"time":0,"x":0,"y":0,"curve":"stepped"},{"time":0.8,"x":0,"y":0,"curve":[0.25,0,0.75,1]},{"time":0.9,"x":-40,"y":0,"curve":[0.25,0,0.75,1]},{"time":1,"x":-120,"y":0,"curve":[0.25,0,0.75,1]},{"time":1.1,"x":-40,"y":0,"curve":[0.25,0,0.75,1]},{"time":1.2,"x":0,"y":0,"curve":[0.25,0,0.75,1]},{"time":1.3,"x":-40,"y":0,"curve":[0.25,0,0.75,1]},{"time":1.4,"x":-120,"y":0,"curve":[0.25,0,0.75,1]},{"time":1.5,"x":-40,"y":0,"curve":[0.25,0,0.75,1]},{"time":1.6,"x":0,"y":0,"curve":[0.25,0,0.75,1]},{"time":1.7,"x":-40,"y":0,"curve":[0.25,0,0.75,1]},{"time":1.8,"x":-120,"y":0,"curve":[0.25,0,0.75,1]},{"time":1.9,"x":-40,"y":0,"curve":[0.25,0,0.75,1]},{"time":2,"x":0,"y":0,"curve":[0.25,0,0.75,1]},{"time":2.1,"x":-40,"y":0,"curve":[0.25,0,0.75,1]},{"time":2.2,"x":-120,"y":0,"curve":[0.25,0,0.75,1]},{"time":2.3,"x":-40,"y":0,"curve":[0.25,0,0.75,1]},{"time":2.4,"x":0,"y":0}]},"bone7":{"shear":[{"time":0,"x":0,"y":0,"curve":"stepped"},{"time":0.8,"x":0,"y":0,"curve":[0.25,0,0.75,1]},{"time":0.9,"x":40,"y":0,"curve":[0.25,0,0.75,1]},{"time":1,"x":120,"y":0,"curve":[0.25,0,0.75,1]},{"time":1.1,"x":40,"y":0,"curve":[0.25,0,0.75,1]},{"time":1.2,"x":0,"y":0,"curve":[0.25,0,0.75,1]},{"time":1.3,"x":40,"y":0,"curve":[0.25,0,0.75,1]},{"time":1.4,"x":120,"y":0,"curve":[0.25,0,0.75,1]},{"time":1.5,"x":40,"y":0,"curve":[0.25,0,0.75,1]},{"time":1.6,"x":0,"y":0,"curve":[0.25,0,0.75,1]},{"time":1.7,"x":40,"y":0,"curve":[0.25,0,0.75,1]},{"time":1.8,"x":120,"y":0,"curve":[0.25,0,0.75,1]},{"time":1.9,"x":40,"y":0,"curve":[0.25,0,0.75,1]},{"time":2,"x":0,"y":0,"curve":[0.25,0,0.75,1]},{"time":2.1,"x":40,"y":0,"curve":[0.25,0,0.75,1]},{"time":2.2,"x":120,"y":0,"curve":[0.25,0,0.75,1]},{"time":2.3,"x":40,"y":0,"curve":[0.25,0,0.75,1]},{"time":2.4,"x":0,"y":0}]},"蝴蝶2":{"rotate":[{"time":0,"angle":23.39,"curve":"stepped"},{"time":0.8333,"angle":23.39}],"translate":[{"time":0,"x":-373.55,"y":-52.16,"curve":"stepped"},{"time":0.7667,"x":-373.55,"y":-52.16,"curve":[0.25,0,0.75,1]},{"time":2.5,"x":-496.46,"y":-181.78}],"scale":[{"time":0,"x":0.7,"y":0.7,"curve":"stepped"},{"time":0.8333,"x":0.7,"y":0.7}]},"bone10":{"shear":[{"time":0,"x":0,"y":0,"curve":"stepped"},{"time":0.8,"x":0,"y":0,"curve":[0.25,0,0.75,1]},{"time":0.9,"x":-40,"y":0,"curve":[0.25,0,0.75,1]},{"time":1,"x":-120,"y":0,"curve":[0.25,0,0.75,1]},{"time":1.1,"x":-40,"y":0,"curve":[0.25,0,0.75,1]},{"time":1.2,"x":0,"y":0,"curve":[0.25,0,0.75,1]},{"time":1.3,"x":-40,"y":0,"curve":[0.25,0,0.75,1]},{"time":1.4,"x":-120,"y":0,"curve":[0.25,0,0.75,1]},{"time":1.5,"x":-40,"y":0,"curve":[0.25,0,0.75,1]},{"time":1.6,"x":0,"y":0,"curve":[0.25,0,0.75,1]},{"time":1.7,"x":-40,"y":0,"curve":[0.25,0,0.75,1]},{"time":1.8,"x":-120,"y":0,"curve":[0.25,0,0.75,1]},{"time":1.9,"x":-40,"y":0,"curve":[0.25,0,0.75,1]},{"time":2,"x":0,"y":0,"curve":[0.25,0,0.75,1]},{"time":2.1,"x":-40,"y":0,"curve":[0.25,0,0.75,1]},{"time":2.2,"x":-120,"y":0,"curve":[0.25,0,0.75,1]},{"time":2.3,"x":-40,"y":0,"curve":[0.25,0,0.75,1]},{"time":2.4,"x":0,"y":0}]},"bone20":{"shear":[{"time":0,"x":0,"y":0,"curve":"stepped"},{"time":0.6333,"x":0,"y":0,"curve":[0.25,0,0.75,1]},{"time":0.7333,"x":40,"y":0,"curve":[0.25,0,0.75,1]},{"time":0.8333,"x":120,"y":0,"curve":[0.25,0,0.75,1]},{"time":0.9333,"x":40.37,"y":0,"curve":[0.25,0,0.75,1]},{"time":1.0333,"x":0,"y":0,"curve":[0.25,0,0.75,1]},{"time":1.1333,"x":40,"y":0,"curve":[0.25,0,0.75,1]},{"time":1.2333,"x":120,"y":0,"curve":[0.25,0,0.75,1]},{"time":1.3333,"x":40.37,"y":0,"curve":[0.25,0,0.75,1]},{"time":1.4333,"x":0,"y":0,"curve":[0.25,0,0.75,1]},{"time":1.5333,"x":40,"y":0,"curve":[0.25,0,0.75,1]},{"time":1.6333,"x":120,"y":0,"curve":[0.25,0,0.75,1]},{"time":1.7333,"x":40.37,"y":0,"curve":[0.25,0,0.75,1]},{"time":1.8333,"x":0,"y":0,"curve":[0.25,0,0.75,1]},{"time":1.9333,"x":40,"y":0,"curve":[0.25,0,0.75,1]},{"time":2.0333,"x":120,"y":0,"curve":[0.25,0,0.75,1]},{"time":2.1333,"x":40.37,"y":0,"curve":[0.25,0,0.75,1]},{"time":2.2333,"x":0,"y":0,"curve":[0.25,0,0.75,1]},{"time":2.3333,"x":40,"y":0,"curve":[0.25,0,0.75,1]},{"time":2.4333,"x":120,"y":0,"curve":[0.25,0,0.75,1]},{"time":2.5333,"x":40.37,"y":0,"curve":[0.25,0,0.75,1]},{"time":2.6333,"x":0,"y":0}]},"bone16":{"shear":[{"time":0,"x":0,"y":0,"curve":"stepped"},{"time":0.8667,"x":0,"y":0,"curve":[0.25,0,0.75,1]},{"time":0.9667,"x":40,"y":0,"curve":[0.25,0,0.75,1]},{"time":1.0667,"x":120,"y":0,"curve":[0.25,0,0.75,1]},{"time":1.1667,"x":40.37,"y":0,"curve":[0.25,0,0.75,1]},{"time":1.2667,"x":0,"y":0,"curve":[0.25,0,0.75,1]},{"time":1.3667,"x":40,"y":0,"curve":[0.25,0,0.75,1]},{"time":1.4667,"x":120,"y":0,"curve":[0.25,0,0.75,1]},{"time":1.5667,"x":40.37,"y":0,"curve":[0.25,0,0.75,1]},{"time":1.6667,"x":0,"y":0,"curve":[0.25,0,0.75,1]},{"time":1.7667,"x":40,"y":0,"curve":[0.25,0,0.75,1]},{"time":1.8667,"x":120,"y":0,"curve":[0.25,0,0.75,1]},{"time":1.9667,"x":40.37,"y":0,"curve":[0.25,0,0.75,1]},{"time":2.0667,"x":0,"y":0,"curve":[0.25,0,0.75,1]},{"time":2.1667,"x":40,"y":0,"curve":[0.25,0,0.75,1]},{"time":2.2667,"x":120,"y":0,"curve":[0.25,0,0.75,1]},{"time":2.3667,"x":40.37,"y":0,"curve":[0.25,0,0.75,1]},{"time":2.4667,"x":0,"y":0,"curve":[0.25,0,0.75,1]},{"time":2.5667,"x":40,"y":0,"curve":[0.25,0,0.75,1]},{"time":2.6667,"x":120,"y":0}]},"蝴蝶3":{"rotate":[{"time":0,"angle":9.58,"curve":"stepped"},{"time":0.8667,"angle":9.58}],"translate":[{"time":0,"x":-344.22,"y":46.37,"curve":"stepped"},{"time":0.8,"x":-344.22,"y":46.37,"curve":[0.25,0,0.75,1]},{"time":2.1333,"x":-509.09,"y":126.4}],"scale":[{"time":0,"x":0.5,"y":0.5,"curve":"stepped"},{"time":0.8667,"x":0.5,"y":0.5}]},"蝴蝶1":{"rotate":[{"time":0,"angle":-24.07,"curve":"stepped"},{"time":0.9333,"angle":-24.07}],"translate":[{"time":0,"x":-32.16,"y":0,"curve":"stepped"},{"time":0.9333,"x":-32.16,"y":0,"curve":[0.25,0,0.75,1]},{"time":1.9333,"x":169.71,"y":5.83}],"scale":[{"time":0,"x":0.9,"y":0.9,"curve":"stepped"},{"time":0.9333,"x":0.9,"y":0.9}],"shear":[{"time":0,"x":0,"y":1.2,"curve":"stepped"},{"time":0.9333,"x":0,"y":1.2}]},"bone19":{"shear":[{"time":0,"x":0,"y":0,"curve":[0.25,0,0.75,1]},{"time":0.7333,"x":-120,"y":0,"curve":[0.25,0,0.75,1]},{"time":0.8333,"x":-40,"y":0,"curve":[0.25,0,0.75,1]},{"time":0.9333,"x":0,"y":0,"curve":[0.25,0,0.75,1]},{"time":1.0333,"x":-40,"y":0,"curve":[0.25,0,0.75,1]},{"time":1.1333,"x":-120,"y":0,"curve":[0.25,0,0.75,1]},{"time":1.2333,"x":-40,"y":0,"curve":[0.25,0,0.75,1]},{"time":1.3333,"x":0,"y":0,"curve":[0.25,0,0.75,1]},{"time":1.4333,"x":-40,"y":0,"curve":[0.25,0,0.75,1]},{"time":1.5333,"x":-120,"y":0,"curve":[0.25,0,0.75,1]},{"time":1.6333,"x":-40,"y":0,"curve":[0.25,0,0.75,1]},{"time":1.7333,"x":0,"y":0,"curve":[0.25,0,0.75,1]},{"time":1.8333,"x":-40,"y":0,"curve":[0.25,0,0.75,1]},{"time":1.9333,"x":-120,"y":0,"curve":[0.25,0,0.75,1]},{"time":2.0333,"x":-40,"y":0,"curve":[0.25,0,0.75,1]},{"time":2.1333,"x":0,"y":0,"curve":[0.25,0,0.75,1]},{"time":2.2333,"x":-40,"y":0,"curve":[0.25,0,0.75,1]},{"time":2.3333,"x":-120,"y":0,"curve":[0.25,0,0.75,1]},{"time":2.4333,"x":-40,"y":0,"curve":[0.25,0,0.75,1]},{"time":2.5333,"x":0,"y":0,"curve":[0.25,0,0.75,1]},{"time":2.6333,"x":-40,"y":0}]},"bone12":{"shear":[{"time":0,"x":0,"y":0,"curve":"stepped"},{"time":0.7667,"x":0,"y":0,"curve":[0.25,0,0.75,1]},{"time":0.8667,"x":-40,"y":0,"curve":[0.25,0,0.75,1]},{"time":0.9667,"x":-120,"y":0,"curve":[0.25,0,0.75,1]},{"time":1.0667,"x":-40,"y":0,"curve":[0.25,0,0.75,1]},{"time":1.1667,"x":0,"y":0,"curve":[0.25,0,0.75,1]},{"time":1.2667,"x":-40,"y":0,"curve":[0.25,0,0.75,1]},{"time":1.3667,"x":-120,"y":0,"curve":[0.25,0,0.75,1]},{"time":1.4667,"x":-40,"y":0,"curve":[0.25,0,0.75,1]},{"time":1.5667,"x":0,"y":0,"curve":[0.25,0,0.75,1]},{"time":1.6667,"x":-40,"y":0,"curve":[0.25,0,0.75,1]},{"time":1.7667,"x":-120,"y":0,"curve":[0.25,0,0.75,1]},{"time":1.8667,"x":-40,"y":0,"curve":[0.25,0,0.75,1]},{"time":1.9667,"x":0,"y":0,"curve":[0.25,0,0.75,1]},{"time":2.0667,"x":-40,"y":0,"curve":[0.25,0,0.75,1]},{"time":2.1667,"x":-120,"y":0,"curve":[0.25,0,0.75,1]},{"time":2.2667,"x":-40,"y":0,"curve":[0.25,0,0.75,1]},{"time":2.3667,"x":0,"y":0}]},"晋升成功":{"translate":[{"time":0,"x":0,"y":-308.7}]},"星星":{"translate":[{"time":0,"x":-96.93,"y":7.2,"curve":"stepped"},{"time":1,"x":-96.93,"y":7.2}],"scale":[{"time":0,"x":0.2,"y":0.2,"curve":"stepped"},{"time":1.0667,"x":0.2,"y":0.2,"curve":[0.25,0,0.75,1]},{"time":2.3333,"x":1.4,"y":1.4}]}},"deform":{"default":{"图层 1":{"图层 1":[{"time":1.6667,"vertices":[-720.50464,0,0,0,0,0,-720.50464],"curve":[0.25,0,0.75,1]},{"time":2}]},"蝴蝶1":{"蝴蝶1":[{"time":0,"vertices":[1.47252,-1.4962,-3.69925,6.44755,-2.11308,-0.83325,0.96904,-7.12688],"curve":"stepped"},{"time":0.9333,"vertices":[1.47252,-1.4962,-3.69925,6.44755,-2.11308,-0.83325,0.96904,-7.12688],"curve":[0.25,0,0.75,1]},{"time":1.0333,"vertices":[1.04185,1.95934,-10.31699,18.84512,1.1136,-6.83831,4.86111,-13.89624],"curve":[0.25,0,0.75,1]},{"time":1.1333,"vertices":[1.47252,-1.4962,-3.69925,6.44755,-2.11308,-0.83325,0.96904,-7.12688],"curve":[0.25,0,0.75,1]},{"time":1.2333,"offset":4,"vertices":[-0.03547,0.1836],"curve":[0.25,0,0.75,1]},{"time":1.3333,"vertices":[1.47252,-1.4962,-3.69925,6.44755,-2.11308,-0.83325,0.96904,-7.12688],"curve":[0.25,0,0.75,1]},{"time":1.4333,"vertices":[1.04185,1.95934,-10.31699,18.84512,1.1136,-6.83831,4.86111,-13.89624],"curve":[0.25,0,0.75,1]},{"time":1.5333,"vertices":[1.47252,-1.4962,-3.69925,6.44755,-2.11308,-0.83325,0.96904,-7.12688],"curve":[0.25,0,0.75,1]},{"time":1.6333,"offset":4,"vertices":[-0.03547,0.1836],"curve":[0.25,0,0.75,1]},{"time":1.7333,"vertices":[1.47252,-1.4962,-3.69925,6.44755,-2.11308,-0.83325,0.96904,-7.12688],"curve":[0.25,0,0.75,1]},{"time":1.8333,"vertices":[1.04185,1.95934,-10.31699,18.84512,1.1136,-6.83831,4.86111,-13.89624],"curve":[0.25,0,0.75,1]},{"time":1.9333,"vertices":[1.47252,-1.4962,-3.69925,6.44755,-2.11308,-0.83325,0.96904,-7.12688],"curve":[0.25,0,0.75,1]},{"time":2.0333,"offset":4,"vertices":[-0.03547,0.1836],"curve":[0.25,0,0.75,1]},{"time":2.1333,"vertices":[1.47252,-1.4962,-3.69925,6.44755,-2.11308,-0.83325,0.96904,-7.12688],"curve":[0.25,0,0.75,1]},{"time":2.2333,"vertices":[1.04185,1.95934,-10.31699,18.84512,1.1136,-6.83831,4.86111,-13.89624]}]},"蝴蝶7":{"蝴蝶1":[{"time":0,"offset":4,"vertices":[-0.03547,0.1836],"curve":"stepped"},{"time":1,"offset":4,"vertices":[-0.03547,0.1836],"curve":[0.25,0,0.75,1]},{"time":1.1,"vertices":[1.47252,-1.4962,-3.69925,6.44755,-2.11308,-0.83325,0.96904,-7.12688],"curve":[0.25,0,0.75,1]},{"time":1.2,"vertices":[1.04185,1.95934,-10.31699,18.84512,1.1136,-6.83831,4.86111,-13.89624],"curve":[0.25,0,0.75,1]},{"time":1.3,"vertices":[1.47252,-1.4962,-3.69925,6.44755,-2.11308,-0.83325,0.96904,-7.12688],"curve":[0.25,0,0.75,1]},{"time":1.4,"offset":4,"vertices":[-0.03547,0.1836],"curve":[0.25,0,0.75,1]},{"time":1.5,"vertices":[1.47252,-1.4962,-3.69925,6.44755,-2.11308,-0.83325,0.96904,-7.12688],"curve":[0.25,0,0.75,1]},{"time":1.6,"vertices":[1.04185,1.95934,-10.31699,18.84512,1.1136,-6.83831,4.86111,-13.89624],"curve":[0.25,0,0.75,1]},{"time":1.7,"vertices":[1.47252,-1.4962,-3.69925,6.44755,-2.11308,-0.83325,0.96904,-7.12688],"curve":[0.25,0,0.75,1]},{"time":1.8,"offset":4,"vertices":[-0.03547,0.1836],"curve":[0.25,0,0.75,1]},{"time":1.9,"vertices":[1.47252,-1.4962,-3.69925,6.44755,-2.11308,-0.83325,0.96904,-7.12688],"curve":[0.25,0,0.75,1]},{"time":2,"vertices":[1.04185,1.95934,-10.31699,18.84512,1.1136,-6.83831,4.86111,-13.89624],"curve":[0.25,0,0.75,1]},{"time":2.1,"vertices":[1.47252,-1.4962,-3.69925,6.44755,-2.11308,-0.83325,0.96904,-7.12688],"curve":[0.25,0,0.75,1]},{"time":2.2,"offset":4,"vertices":[-0.03547,0.1836],"curve":[0.25,0,0.75,1]},{"time":2.3,"vertices":[1.47252,-1.4962,-3.69925,6.44755,-2.11308,-0.83325,0.96904,-7.12688],"curve":[0.25,0,0.75,1]},{"time":2.4,"vertices":[1.04185,1.95934,-10.31699,18.84512,1.1136,-6.83831,4.86111,-13.89624],"curve":[0.25,0,0.75,1]},{"time":2.5,"vertices":[1.47252,-1.4962,-3.69925,6.44755,-2.11308,-0.83325,0.96904,-7.12688],"curve":[0.25,0,0.75,1]},{"time":2.6,"offset":4,"vertices":[-0.03547,0.1836]}]},"蝴蝶8":{"蝴蝶1":[{"time":0,"offset":4,"vertices":[-0.03547,0.1836],"curve":"stepped"},{"time":0.8667,"offset":4,"vertices":[-0.03547,0.1836],"curve":[0.25,0,0.75,1]},{"time":0.9667,"vertices":[1.47252,-1.4962,-3.69925,6.44755,-2.11308,-0.83325,0.96904,-7.12688],"curve":[0.25,0,0.75,1]},{"time":1.0667,"vertices":[1.04185,1.95934,-10.31699,18.84512,1.1136,-6.83831,4.86111,-13.89624],"curve":[0.25,0,0.75,1]},{"time":1.1667,"vertices":[1.47252,-1.4962,-3.69925,6.44755,-2.11308,-0.83325,0.96904,-7.12688],"curve":[0.25,0,0.75,1]},{"time":1.2667,"offset":4,"vertices":[-0.03547,0.1836],"curve":[0.25,0,0.75,1]},{"time":1.3667,"vertices":[1.47252,-1.4962,-3.69925,6.44755,-2.11308,-0.83325,0.96904,-7.12688],"curve":[0.25,0,0.75,1]},{"time":1.4667,"vertices":[1.04185,1.95934,-10.31699,18.84512,1.1136,-6.83831,4.86111,-13.89624],"curve":[0.25,0,0.75,1]},{"time":1.5667,"vertices":[1.47252,-1.4962,-3.69925,6.44755,-2.11308,-0.83325,0.96904,-7.12688],"curve":[0.25,0,0.75,1]},{"time":1.6667,"offset":4,"vertices":[-0.03547,0.1836],"curve":[0.25,0,0.75,1]},{"time":1.7667,"vertices":[1.47252,-1.4962,-3.69925,6.44755,-2.11308,-0.83325,0.96904,-7.12688],"curve":[0.25,0,0.75,1]},{"time":1.8667,"vertices":[1.04185,1.95934,-10.31699,18.84512,1.1136,-6.83831,4.86111,-13.89624],"curve":[0.25,0,0.75,1]},{"time":1.9667,"vertices":[1.47252,-1.4962,-3.69925,6.44755,-2.11308,-0.83325,0.96904,-7.12688],"curve":[0.25,0,0.75,1]},{"time":2.0667,"offset":4,"vertices":[-0.03547,0.1836],"curve":[0.25,0,0.75,1]},{"time":2.1667,"vertices":[1.47252,-1.4962,-3.69925,6.44755,-2.11308,-0.83325,0.96904,-7.12688],"curve":[0.25,0,0.75,1]},{"time":2.2667,"vertices":[1.04185,1.95934,-10.31699,18.84512,1.1136,-6.83831,4.86111,-13.89624],"curve":[0.25,0,0.75,1]},{"time":2.3667,"vertices":[1.47252,-1.4962,-3.69925,6.44755,-2.11308,-0.83325,0.96904,-7.12688],"curve":[0.25,0,0.75,1]},{"time":2.4667,"offset":4,"vertices":[-0.03547,0.1836],"curve":[0.25,0,0.75,1]},{"time":2.5667,"vertices":[1.47252,-1.4962,-3.69925,6.44755,-2.11308,-0.83325,0.96904,-7.12688],"curve":[0.25,0,0.75,1]},{"time":2.6667,"vertices":[1.04185,1.95934,-10.31699,18.84512,1.1136,-6.83831,4.86111,-13.89624]}]},"蝴蝶9":{"蝴蝶1":[{"time":0,"offset":4,"vertices":[-0.03547,0.1836],"curve":[0.25,0,0.75,1]},{"time":0.7333,"vertices":[1.04185,1.95934,-10.31699,18.84512,1.1136,-6.83831,4.86111,-13.89624],"curve":[0.25,0,0.75,1]},{"time":0.8333,"vertices":[1.47252,-1.4962,-3.69925,6.44755,-2.11308,-0.83325,0.96904,-7.12688],"curve":[0.25,0,0.75,1]},{"time":0.9333,"offset":4,"vertices":[-0.03547,0.1836],"curve":[0.25,0,0.75,1]},{"time":1.0333,"vertices":[1.47252,-1.4962,-3.69925,6.44755,-2.11308,-0.83325,0.96904,-7.12688],"curve":[0.25,0,0.75,1]},{"time":1.1333,"vertices":[1.04185,1.95934,-10.31699,18.84512,1.1136,-6.83831,4.86111,-13.89624],"curve":[0.25,0,0.75,1]},{"time":1.2333,"vertices":[1.47252,-1.4962,-3.69925,6.44755,-2.11308,-0.83325,0.96904,-7.12688],"curve":[0.25,0,0.75,1]},{"time":1.3333,"offset":4,"vertices":[-0.03547,0.1836],"curve":[0.25,0,0.75,1]},{"time":1.4333,"vertices":[1.47252,-1.4962,-3.69925,6.44755,-2.11308,-0.83325,0.96904,-7.12688],"curve":[0.25,0,0.75,1]},{"time":1.5333,"vertices":[1.04185,1.95934,-10.31699,18.84512,1.1136,-6.83831,4.86111,-13.89624],"curve":[0.25,0,0.75,1]},{"time":1.6333,"vertices":[1.47252,-1.4962,-3.69925,6.44755,-2.11308,-0.83325,0.96904,-7.12688],"curve":[0.25,0,0.75,1]},{"time":1.7333,"offset":4,"vertices":[-0.03547,0.1836],"curve":[0.25,0,0.75,1]},{"time":1.8333,"vertices":[1.47252,-1.4962,-3.69925,6.44755,-2.11308,-0.83325,0.96904,-7.12688],"curve":[0.25,0,0.75,1]},{"time":1.9333,"vertices":[1.04185,1.95934,-10.31699,18.84512,1.1136,-6.83831,4.86111,-13.89624],"curve":[0.25,0,0.75,1]},{"time":2.0333,"vertices":[1.47252,-1.4962,-3.69925,6.44755,-2.11308,-0.83325,0.96904,-7.12688],"curve":[0.25,0,0.75,1]},{"time":2.1333,"offset":4,"vertices":[-0.03547,0.1836],"curve":[0.25,0,0.75,1]},{"time":2.2333,"vertices":[1.47252,-1.4962,-3.69925,6.44755,-2.11308,-0.83325,0.96904,-7.12688],"curve":[0.25,0,0.75,1]},{"time":2.3333,"vertices":[1.04185,1.95934,-10.31699,18.84512,1.1136,-6.83831,4.86111,-13.89624],"curve":[0.25,0,0.75,1]},{"time":2.4333,"vertices":[1.47252,-1.4962,-3.69925,6.44755,-2.11308,-0.83325,0.96904,-7.12688],"curve":[0.25,0,0.75,1]},{"time":2.5333,"offset":4,"vertices":[-0.03547,0.1836],"curve":[0.25,0,0.75,1]},{"time":2.6333,"vertices":[1.47252,-1.4962,-3.69925,6.44755,-2.11308,-0.83325,0.96904,-7.12688]}]},"蝴蝶10":{"蝴蝶1":[{"time":0,"offset":4,"vertices":[-0.03547,0.1836],"curve":"stepped"},{"time":0.6333,"offset":4,"vertices":[-0.03547,0.1836],"curve":[0.25,0,0.75,1]},{"time":0.7333,"vertices":[1.47252,-1.4962,-3.69925,6.44755,-2.11308,-0.83325,0.96904,-7.12688],"curve":[0.25,0,0.75,1]},{"time":0.8333,"vertices":[1.04185,1.95934,-10.31699,18.84512,1.1136,-6.83831,4.86111,-13.89624],"curve":[0.25,0,0.75,1]},{"time":0.9333,"vertices":[1.47252,-1.4962,-3.69925,6.44755,-2.11308,-0.83325,0.96904,-7.12688],"curve":[0.25,0,0.75,1]},{"time":1.0333,"offset":4,"vertices":[-0.03547,0.1836],"curve":[0.25,0,0.75,1]},{"time":1.1333,"vertices":[1.47252,-1.4962,-3.69925,6.44755,-2.11308,-0.83325,0.96904,-7.12688],"curve":[0.25,0,0.75,1]},{"time":1.2333,"vertices":[1.04185,1.95934,-10.31699,18.84512,1.1136,-6.83831,4.86111,-13.89624],"curve":[0.25,0,0.75,1]},{"time":1.3333,"vertices":[1.47252,-1.4962,-3.69925,6.44755,-2.11308,-0.83325,0.96904,-7.12688],"curve":[0.25,0,0.75,1]},{"time":1.4333,"offset":4,"vertices":[-0.03547,0.1836],"curve":[0.25,0,0.75,1]},{"time":1.5333,"vertices":[1.47252,-1.4962,-3.69925,6.44755,-2.11308,-0.83325,0.96904,-7.12688],"curve":[0.25,0,0.75,1]},{"time":1.6333,"vertices":[1.04185,1.95934,-10.31699,18.84512,1.1136,-6.83831,4.86111,-13.89624],"curve":[0.25,0,0.75,1]},{"time":1.7333,"vertices":[1.47252,-1.4962,-3.69925,6.44755,-2.11308,-0.83325,0.96904,-7.12688],"curve":[0.25,0,0.75,1]},{"time":1.8333,"offset":4,"vertices":[-0.03547,0.1836],"curve":[0.25,0,0.75,1]},{"time":1.9333,"vertices":[1.47252,-1.4962,-3.69925,6.44755,-2.11308,-0.83325,0.96904,-7.12688],"curve":[0.25,0,0.75,1]},{"time":2.0333,"vertices":[1.04185,1.95934,-10.31699,18.84512,1.1136,-6.83831,4.86111,-13.89624],"curve":[0.25,0,0.75,1]},{"time":2.1333,"vertices":[1.47252,-1.4962,-3.69925,6.44755,-2.11308,-0.83325,0.96904,-7.12688],"curve":[0.25,0,0.75,1]},{"time":2.2333,"offset":4,"vertices":[-0.03547,0.1836],"curve":[0.25,0,0.75,1]},{"time":2.3333,"vertices":[1.47252,-1.4962,-3.69925,6.44755,-2.11308,-0.83325,0.96904,-7.12688],"curve":[0.25,0,0.75,1]},{"time":2.4333,"vertices":[1.04185,1.95934,-10.31699,18.84512,1.1136,-6.83831,4.86111,-13.89624],"curve":[0.25,0,0.75,1]},{"time":2.5333,"vertices":[1.47252,-1.4962,-3.69925,6.44755,-2.11308,-0.83325,0.96904,-7.12688],"curve":[0.25,0,0.75,1]},{"time":2.6333,"offset":4,"vertices":[-0.03547,0.1836]}]},"蝴蝶1-2":{"蝴蝶1-2":[{"time":0,"vertices":[-9.46638,15.6194,0,0,-2.1E-4,9.55748,-9.46676,28.27412],"curve":"stepped"},{"time":0.9333,"vertices":[-9.46638,15.6194,0,0,-2.1E-4,9.55748,-9.46676,28.27412],"curve":[0.25,0,0.75,1]},{"time":1.0333,"vertices":[-14.8762,24.34565,-0.07466,-4.55554,15.92896,29.49945,17.24176,73.56074],"curve":[0.25,0,0.75,1]},{"time":1.1333,"vertices":[-9.46638,15.6194,0,0,-2.1E-4,9.55748,-9.46676,28.27412],"curve":[0.25,0,0.75,1]},{"time":1.2333,"offset":7,"vertices":[-0.01797],"curve":[0.25,0,0.75,1]},{"time":1.3333,"vertices":[-9.46638,15.6194,0,0,-2.1E-4,9.55748,-9.46676,28.27412],"curve":[0.25,0,0.75,1]},{"time":1.4333,"vertices":[-14.8762,24.34565,-0.07466,-4.55554,15.92896,29.49945,17.24176,73.56074],"curve":[0.25,0,0.75,1]},{"time":1.5333,"vertices":[-9.46638,15.6194,0,0,-2.1E-4,9.55748,-9.46676,28.27412],"curve":[0.25,0,0.75,1]},{"time":1.6333,"offset":7,"vertices":[-0.01797],"curve":[0.25,0,0.75,1]},{"time":1.7333,"vertices":[-9.46638,15.6194,0,0,-2.1E-4,9.55748,-9.46676,28.27412],"curve":[0.25,0,0.75,1]},{"time":1.8333,"vertices":[-14.8762,24.34565,-0.07466,-4.55554,15.92896,29.49945,17.24176,73.56074],"curve":[0.25,0,0.75,1]},{"time":1.9333,"vertices":[-9.46638,15.6194,0,0,-2.1E-4,9.55748,-9.46676,28.27412],"curve":[0.25,0,0.75,1]},{"time":2.0333,"offset":7,"vertices":[-0.01797],"curve":[0.25,0,0.75,1]},{"time":2.1333,"vertices":[-9.46638,15.6194,0,0,-2.1E-4,9.55748,-9.46676,28.27412],"curve":[0.25,0,0.75,1]},{"time":2.2333,"vertices":[-14.8762,24.34565,-0.07466,-4.55554,15.92896,29.49945,17.24176,73.56074]}]},"蝴蝶1-4":{"蝴蝶1-2":[{"time":0,"offset":7,"vertices":[-0.01797],"curve":"stepped"},{"time":1,"offset":7,"vertices":[-0.01797],"curve":[0.25,0,0.75,1]},{"time":1.1,"vertices":[-9.46638,15.6194,0,0,-2.1E-4,9.55748,-9.46676,28.27412],"curve":[0.25,0,0.75,1]},{"time":1.2,"vertices":[-14.8762,24.34565,-0.07466,-4.55554,15.92896,29.49945,17.24176,73.56074],"curve":[0.25,0,0.75,1]},{"time":1.3,"vertices":[-9.46638,15.6194,0,0,-2.1E-4,9.55748,-9.46676,28.27412],"curve":[0.25,0,0.75,1]},{"time":1.4,"offset":7,"vertices":[-0.01797],"curve":[0.25,0,0.75,1]},{"time":1.5,"vertices":[-9.46638,15.6194,0,0,-2.1E-4,9.55748,-9.46676,28.27412],"curve":[0.25,0,0.75,1]},{"time":1.6,"vertices":[-14.8762,24.34565,-0.07466,-4.55554,15.92896,29.49945,17.24176,73.56074],"curve":[0.25,0,0.75,1]},{"time":1.7,"vertices":[-9.46638,15.6194,0,0,-2.1E-4,9.55748,-9.46676,28.27412],"curve":[0.25,0,0.75,1]},{"time":1.8,"offset":7,"vertices":[-0.01797],"curve":[0.25,0,0.75,1]},{"time":1.9,"vertices":[-9.46638,15.6194,0,0,-2.1E-4,9.55748,-9.46676,28.27412],"curve":[0.25,0,0.75,1]},{"time":2,"vertices":[-14.8762,24.34565,-0.07466,-4.55554,15.92896,29.49945,17.24176,73.56074],"curve":[0.25,0,0.75,1]},{"time":2.1,"vertices":[-9.46638,15.6194,0,0,-2.1E-4,9.55748,-9.46676,28.27412],"curve":[0.25,0,0.75,1]},{"time":2.2,"offset":7,"vertices":[-0.01797],"curve":[0.25,0,0.75,1]},{"time":2.3,"vertices":[-9.46638,15.6194,0,0,-2.1E-4,9.55748,-9.46676,28.27412],"curve":[0.25,0,0.75,1]},{"time":2.4,"vertices":[-14.8762,24.34565,-0.07466,-4.55554,15.92896,29.49945,17.24176,73.56074],"curve":[0.25,0,0.75,1]},{"time":2.5,"vertices":[-9.46638,15.6194,0,0,-2.1E-4,9.55748,-9.46676,28.27412],"curve":[0.25,0,0.75,1]},{"time":2.6,"offset":7,"vertices":[-0.01797]}]},"蝴蝶1-6":{"蝴蝶1-2":[{"time":0,"offset":7,"vertices":[-0.01797],"curve":"stepped"},{"time":0.8667,"offset":7,"vertices":[-0.01797],"curve":[0.25,0,0.75,1]},{"time":0.9667,"vertices":[-9.46638,15.6194,0,0,-2.1E-4,9.55748,-9.46676,28.27412],"curve":[0.25,0,0.75,1]},{"time":1.0667,"vertices":[-14.8762,24.34565,-0.07466,-4.55554,15.92896,29.49945,17.24176,73.56074],"curve":[0.25,0,0.75,1]},{"time":1.1667,"vertices":[-9.46638,15.6194,0,0,-2.1E-4,9.55748,-9.46676,28.27412],"curve":[0.25,0,0.75,1]},{"time":1.2667,"offset":7,"vertices":[-0.01797],"curve":[0.25,0,0.75,1]},{"time":1.3667,"vertices":[-9.46638,15.6194,0,0,-2.1E-4,9.55748,-9.46676,28.27412],"curve":[0.25,0,0.75,1]},{"time":1.4667,"vertices":[-14.8762,24.34565,-0.07466,-4.55554,15.92896,29.49945,17.24176,73.56074],"curve":[0.25,0,0.75,1]},{"time":1.5667,"vertices":[-9.46638,15.6194,0,0,-2.1E-4,9.55748,-9.46676,28.27412],"curve":[0.25,0,0.75,1]},{"time":1.6667,"offset":7,"vertices":[-0.01797],"curve":[0.25,0,0.75,1]},{"time":1.7667,"vertices":[-9.46638,15.6194,0,0,-2.1E-4,9.55748,-9.46676,28.27412],"curve":[0.25,0,0.75,1]},{"time":1.8667,"vertices":[-14.8762,24.34565,-0.07466,-4.55554,15.92896,29.49945,17.24176,73.56074],"curve":[0.25,0,0.75,1]},{"time":1.9667,"vertices":[-9.46638,15.6194,0,0,-2.1E-4,9.55748,-9.46676,28.27412],"curve":[0.25,0,0.75,1]},{"time":2.0667,"offset":7,"vertices":[-0.01797],"curve":[0.25,0,0.75,1]},{"time":2.1667,"vertices":[-9.46638,15.6194,0,0,-2.1E-4,9.55748,-9.46676,28.27412],"curve":[0.25,0,0.75,1]},{"time":2.2667,"vertices":[-14.8762,24.34565,-0.07466,-4.55554,15.92896,29.49945,17.24176,73.56074],"curve":[0.25,0,0.75,1]},{"time":2.3667,"vertices":[-9.46638,15.6194,0,0,-2.1E-4,9.55748,-9.46676,28.27412],"curve":[0.25,0,0.75,1]},{"time":2.4667,"offset":7,"vertices":[-0.01797],"curve":[0.25,0,0.75,1]},{"time":2.5667,"vertices":[-9.46638,15.6194,0,0,-2.1E-4,9.55748,-9.46676,28.27412],"curve":[0.25,0,0.75,1]},{"time":2.6667,"vertices":[-14.8762,24.34565,-0.07466,-4.55554,15.92896,29.49945,17.24176,73.56074]}]},"蝴蝶1-8":{"蝴蝶1-2":[{"time":0,"offset":7,"vertices":[-0.01797],"curve":[0.25,0,0.75,1]},{"time":0.7333,"vertices":[-14.8762,24.34565,-0.07466,-4.55554,15.92896,29.49945,17.24176,73.56074],"curve":[0.25,0,0.75,1]},{"time":0.8333,"vertices":[-9.46638,15.6194,0,0,-2.1E-4,9.55748,-9.46676,28.27412],"curve":[0.25,0,0.75,1]},{"time":0.9333,"offset":7,"vertices":[-0.01797],"curve":[0.25,0,0.75,1]},{"time":1.0333,"vertices":[-9.46638,15.6194,0,0,-2.1E-4,9.55748,-9.46676,28.27412],"curve":[0.25,0,0.75,1]},{"time":1.1333,"vertices":[-14.8762,24.34565,-0.07466,-4.55554,15.92896,29.49945,17.24176,73.56074],"curve":[0.25,0,0.75,1]},{"time":1.2333,"vertices":[-9.46638,15.6194,0,0,-2.1E-4,9.55748,-9.46676,28.27412],"curve":[0.25,0,0.75,1]},{"time":1.3333,"offset":7,"vertices":[-0.01797],"curve":[0.25,0,0.75,1]},{"time":1.4333,"vertices":[-9.46638,15.6194,0,0,-2.1E-4,9.55748,-9.46676,28.27412],"curve":[0.25,0,0.75,1]},{"time":1.5333,"vertices":[-14.8762,24.34565,-0.07466,-4.55554,15.92896,29.49945,17.24176,73.56074],"curve":[0.25,0,0.75,1]},{"time":1.6333,"vertices":[-9.46638,15.6194,0,0,-2.1E-4,9.55748,-9.46676,28.27412],"curve":[0.25,0,0.75,1]},{"time":1.7333,"offset":7,"vertices":[-0.01797],"curve":[0.25,0,0.75,1]},{"time":1.8333,"vertices":[-9.46638,15.6194,0,0,-2.1E-4,9.55748,-9.46676,28.27412],"curve":[0.25,0,0.75,1]},{"time":1.9333,"vertices":[-14.8762,24.34565,-0.07466,-4.55554,15.92896,29.49945,17.24176,73.56074],"curve":[0.25,0,0.75,1]},{"time":2.0333,"vertices":[-9.46638,15.6194,0,0,-2.1E-4,9.55748,-9.46676,28.27412],"curve":[0.25,0,0.75,1]},{"time":2.1333,"offset":7,"vertices":[-0.01797],"curve":[0.25,0,0.75,1]},{"time":2.2333,"vertices":[-9.46638,15.6194,0,0,-2.1E-4,9.55748,-9.46676,28.27412],"curve":[0.25,0,0.75,1]},{"time":2.3333,"vertices":[-14.8762,24.34565,-0.07466,-4.55554,15.92896,29.49945,17.24176,73.56074],"curve":[0.25,0,0.75,1]},{"time":2.4333,"vertices":[-9.46638,15.6194,0,0,-2.1E-4,9.55748,-9.46676,28.27412],"curve":[0.25,0,0.75,1]},{"time":2.5333,"offset":7,"vertices":[-0.01797],"curve":[0.25,0,0.75,1]},{"time":2.6333,"vertices":[-9.46638,15.6194,0,0,-2.1E-4,9.55748,-9.46676,28.27412]}]},"蝴蝶1-10":{"蝴蝶1-2":[{"time":0,"offset":7,"vertices":[-0.01797],"curve":"stepped"},{"time":0.6333,"offset":7,"vertices":[-0.01797],"curve":[0.25,0,0.75,1]},{"time":0.7333,"vertices":[-9.46638,15.6194,0,0,-2.1E-4,9.55748,-9.46676,28.27412],"curve":[0.25,0,0.75,1]},{"time":0.8333,"vertices":[-14.8762,24.34565,-0.07466,-4.55554,15.92896,29.49945,17.24176,73.56074],"curve":[0.25,0,0.75,1]},{"time":0.9333,"vertices":[-9.46638,15.6194,0,0,-2.1E-4,9.55748,-9.46676,28.27412],"curve":[0.25,0,0.75,1]},{"time":1.0333,"offset":7,"vertices":[-0.01797],"curve":[0.25,0,0.75,1]},{"time":1.1333,"vertices":[-9.46638,15.6194,0,0,-2.1E-4,9.55748,-9.46676,28.27412],"curve":[0.25,0,0.75,1]},{"time":1.2333,"vertices":[-14.8762,24.34565,-0.07466,-4.55554,15.92896,29.49945,17.24176,73.56074],"curve":[0.25,0,0.75,1]},{"time":1.3333,"vertices":[-9.46638,15.6194,0,0,-2.1E-4,9.55748,-9.46676,28.27412],"curve":[0.25,0,0.75,1]},{"time":1.4333,"offset":7,"vertices":[-0.01797],"curve":[0.25,0,0.75,1]},{"time":1.5333,"vertices":[-9.46638,15.6194,0,0,-2.1E-4,9.55748,-9.46676,28.27412],"curve":[0.25,0,0.75,1]},{"time":1.6333,"vertices":[-14.8762,24.34565,-0.07466,-4.55554,15.92896,29.49945,17.24176,73.56074],"curve":[0.25,0,0.75,1]},{"time":1.7333,"vertices":[-9.46638,15.6194,0,0,-2.1E-4,9.55748,-9.46676,28.27412],"curve":[0.25,0,0.75,1]},{"time":1.8333,"offset":7,"vertices":[-0.01797],"curve":[0.25,0,0.75,1]},{"time":1.9333,"vertices":[-9.46638,15.6194,0,0,-2.1E-4,9.55748,-9.46676,28.27412],"curve":[0.25,0,0.75,1]},{"time":2.0333,"vertices":[-14.8762,24.34565,-0.07466,-4.55554,15.92896,29.49945,17.24176,73.56074],"curve":[0.25,0,0.75,1]},{"time":2.1333,"vertices":[-9.46638,15.6194,0,0,-2.1E-4,9.55748,-9.46676,28.27412],"curve":[0.25,0,0.75,1]},{"time":2.2333,"offset":7,"vertices":[-0.01797],"curve":[0.25,0,0.75,1]},{"time":2.3333,"vertices":[-9.46638,15.6194,0,0,-2.1E-4,9.55748,-9.46676,28.27412],"curve":[0.25,0,0.75,1]},{"time":2.4333,"vertices":[-14.8762,24.34565,-0.07466,-4.55554,15.92896,29.49945,17.24176,73.56074],"curve":[0.25,0,0.75,1]},{"time":2.5333,"vertices":[-9.46638,15.6194,0,0,-2.1E-4,9.55748,-9.46676,28.27412],"curve":[0.25,0,0.75,1]},{"time":2.6333,"offset":7,"vertices":[-0.01797]}]},"蝴蝶2-2":{"蝴蝶2-2":[{"time":0,"curve":"stepped"},{"time":0.7667,"curve":[0.25,0,0.75,1]},{"time":0.8667,"vertices":[-6.02734,-21.07706,0,0,3.03491,-5.17853,-4.80948,-23.91077],"curve":[0.25,0,0.75,1]},{"time":0.9667,"vertices":[-25.23947,-5.7522,3.78441,-11.99461,25.66389,-32.014,0.28458,-29.42257],"curve":[0.25,0,0.75,1]},{"time":1.0667,"vertices":[-6.02734,-21.07706,0,0,3.03491,-5.17853,-4.80948,-23.91077],"curve":[0.25,0,0.75,1]},{"time":1.1667,"curve":[0.25,0,0.75,1]},{"time":1.2667,"vertices":[-6.02734,-21.07706,0,0,3.03491,-5.17853,-4.80948,-23.91077],"curve":[0.25,0,0.75,1]},{"time":1.3667,"vertices":[-25.23947,-5.7522,3.78441,-11.99461,25.66389,-32.014,0.28458,-29.42257],"curve":[0.25,0,0.75,1]},{"time":1.4667,"vertices":[-6.02734,-21.07706,0,0,3.03491,-5.17853,-4.80948,-23.91077],"curve":[0.25,0,0.75,1]},{"time":1.5667,"curve":[0.25,0,0.75,1]},{"time":1.6667,"vertices":[-6.02734,-21.07706,0,0,3.03491,-5.17853,-4.80948,-23.91077],"curve":[0.25,0,0.75,1]},{"time":1.7667,"vertices":[-25.23947,-5.7522,3.78441,-11.99461,25.66389,-32.014,0.28458,-29.42257],"curve":[0.25,0,0.75,1]},{"time":1.8667,"vertices":[-6.02734,-21.07706,0,0,3.03491,-5.17853,-4.80948,-23.91077],"curve":[0.25,0,0.75,1]},{"time":1.9667,"curve":[0.25,0,0.75,1]},{"time":2.0667,"vertices":[-6.02734,-21.07706,0,0,3.03491,-5.17853,-4.80948,-23.91077],"curve":[0.25,0,0.75,1]},{"time":2.1667,"vertices":[-25.23947,-5.7522,3.78441,-11.99461,25.66389,-32.014,0.28458,-29.42257],"curve":[0.25,0,0.75,1]},{"time":2.2667,"vertices":[-6.02734,-21.07706,0,0,3.03491,-5.17853,-4.80948,-23.91077],"curve":[0.25,0,0.75,1]},{"time":2.3667}]},"蝴蝶2-4":{"蝴蝶2-2":[{"time":0,"curve":"stepped"},{"time":0.8,"curve":[0.25,0,0.75,1]},{"time":0.9,"vertices":[-6.02734,-21.07706,0,0,3.03491,-5.17853,-4.80948,-23.91077],"curve":[0.25,0,0.75,1]},{"time":1,"vertices":[-25.23947,-5.7522,3.78441,-11.99461,25.66389,-32.014,0.28458,-29.42257],"curve":[0.25,0,0.75,1]},{"time":1.1,"vertices":[-6.02734,-21.07706,0,0,3.03491,-5.17853,-4.80948,-23.91077],"curve":[0.25,0,0.75,1]},{"time":1.2,"curve":[0.25,0,0.75,1]},{"time":1.3,"vertices":[-6.02734,-21.07706,0,0,3.03491,-5.17853,-4.80948,-23.91077],"curve":[0.25,0,0.75,1]},{"time":1.4,"vertices":[-25.23947,-5.7522,3.78441,-11.99461,25.66389,-32.014,0.28458,-29.42257],"curve":[0.25,0,0.75,1]},{"time":1.5,"vertices":[-6.02734,-21.07706,0,0,3.03491,-5.17853,-4.80948,-23.91077],"curve":[0.25,0,0.75,1]},{"time":1.6,"curve":[0.25,0,0.75,1]},{"time":1.7,"vertices":[-6.02734,-21.07706,0,0,3.03491,-5.17853,-4.80948,-23.91077],"curve":[0.25,0,0.75,1]},{"time":1.8,"vertices":[-25.23947,-5.7522,3.78441,-11.99461,25.66389,-32.014,0.28458,-29.42257],"curve":[0.25,0,0.75,1]},{"time":1.9,"vertices":[-6.02734,-21.07706,0,0,3.03491,-5.17853,-4.80948,-23.91077],"curve":[0.25,0,0.75,1]},{"time":2,"curve":[0.25,0,0.75,1]},{"time":2.1,"vertices":[-6.02734,-21.07706,0,0,3.03491,-5.17853,-4.80948,-23.91077],"curve":[0.25,0,0.75,1]},{"time":2.2,"vertices":[-25.23947,-5.7522,3.78441,-11.99461,25.66389,-32.014,0.28458,-29.42257],"curve":[0.25,0,0.75,1]},{"time":2.3,"vertices":[-6.02734,-21.07706,0,0,3.03491,-5.17853,-4.80948,-23.91077],"curve":[0.25,0,0.75,1]},{"time":2.4}]},"蝴蝶2-8":{"蝴蝶2-2":[{"time":0,"curve":"stepped"},{"time":0.8,"curve":[0.25,0,0.75,1]},{"time":0.9,"vertices":[-6.02734,-21.07706,0,0,3.03491,-5.17853,-4.80948,-23.91077],"curve":[0.25,0,0.75,1]},{"time":1,"vertices":[-25.23947,-5.7522,3.78441,-11.99461,25.66389,-32.014,0.28458,-29.42257],"curve":[0.25,0,0.75,1]},{"time":1.1,"vertices":[-6.02734,-21.07706,0,0,3.03491,-5.17853,-4.80948,-23.91077],"curve":[0.25,0,0.75,1]},{"time":1.2,"curve":[0.25,0,0.75,1]},{"time":1.3,"vertices":[-6.02734,-21.07706,0,0,3.03491,-5.17853,-4.80948,-23.91077],"curve":[0.25,0,0.75,1]},{"time":1.4,"vertices":[-25.23947,-5.7522,3.78441,-11.99461,25.66389,-32.014,0.28458,-29.42257],"curve":[0.25,0,0.75,1]},{"time":1.5,"vertices":[-6.02734,-21.07706,0,0,3.03491,-5.17853,-4.80948,-23.91077],"curve":[0.25,0,0.75,1]},{"time":1.6,"curve":[0.25,0,0.75,1]},{"time":1.7,"vertices":[-6.02734,-21.07706,0,0,3.03491,-5.17853,-4.80948,-23.91077],"curve":[0.25,0,0.75,1]},{"time":1.8,"vertices":[-25.23947,-5.7522,3.78441,-11.99461,25.66389,-32.014,0.28458,-29.42257],"curve":[0.25,0,0.75,1]},{"time":1.9,"vertices":[-6.02734,-21.07706,0,0,3.03491,-5.17853,-4.80948,-23.91077],"curve":[0.25,0,0.75,1]},{"time":2,"curve":[0.25,0,0.75,1]},{"time":2.1,"vertices":[-6.02734,-21.07706,0,0,3.03491,-5.17853,-4.80948,-23.91077],"curve":[0.25,0,0.75,1]},{"time":2.2,"vertices":[-25.23947,-5.7522,3.78441,-11.99461,25.66389,-32.014,0.28458,-29.42257],"curve":[0.25,0,0.75,1]},{"time":2.3,"vertices":[-6.02734,-21.07706,0,0,3.03491,-5.17853,-4.80948,-23.91077],"curve":[0.25,0,0.75,1]},{"time":2.4}]},"蝴蝶2-10":{"蝴蝶2-2":[{"time":0,"curve":"stepped"},{"time":0.7667,"curve":[0.25,0,0.75,1]},{"time":0.8667,"vertices":[-6.02734,-21.07706,0,0,3.03491,-5.17853,-4.80948,-23.91077],"curve":[0.25,0,0.75,1]},{"time":0.9667,"vertices":[-25.23947,-5.7522,3.78441,-11.99461,25.66389,-32.014,0.28458,-29.42257],"curve":[0.25,0,0.75,1]},{"time":1.0667,"vertices":[-6.02734,-21.07706,0,0,3.03491,-5.17853,-4.80948,-23.91077],"curve":[0.25,0,0.75,1]},{"time":1.1667,"curve":[0.25,0,0.75,1]},{"time":1.2667,"vertices":[-6.02734,-21.07706,0,0,3.03491,-5.17853,-4.80948,-23.91077],"curve":[0.25,0,0.75,1]},{"time":1.3667,"vertices":[-25.23947,-5.7522,3.78441,-11.99461,25.66389,-32.014,0.28458,-29.42257],"curve":[0.25,0,0.75,1]},{"time":1.4667,"vertices":[-6.02734,-21.07706,0,0,3.03491,-5.17853,-4.80948,-23.91077],"curve":[0.25,0,0.75,1]},{"time":1.5667,"curve":[0.25,0,0.75,1]},{"time":1.6667,"vertices":[-6.02734,-21.07706,0,0,3.03491,-5.17853,-4.80948,-23.91077],"curve":[0.25,0,0.75,1]},{"time":1.7667,"vertices":[-25.23947,-5.7522,3.78441,-11.99461,25.66389,-32.014,0.28458,-29.42257],"curve":[0.25,0,0.75,1]},{"time":1.8667,"vertices":[-6.02734,-21.07706,0,0,3.03491,-5.17853,-4.80948,-23.91077],"curve":[0.25,0,0.75,1]},{"time":1.9667,"curve":[0.25,0,0.75,1]},{"time":2.0667,"vertices":[-6.02734,-21.07706,0,0,3.03491,-5.17853,-4.80948,-23.91077],"curve":[0.25,0,0.75,1]},{"time":2.1667,"vertices":[-25.23947,-5.7522,3.78441,-11.99461,25.66389,-32.014,0.28458,-29.42257],"curve":[0.25,0,0.75,1]},{"time":2.2667,"vertices":[-6.02734,-21.07706,0,0,3.03491,-5.17853,-4.80948,-23.91077],"curve":[0.25,0,0.75,1]},{"time":2.3667}]}}}},"animation2":{"slots":{"huaban1":{"color":[{"time":0,"color":"ffffff00"}]},"huaban2":{"color":[{"time":0,"color":"ffffff00"}]},"huaban3":{"color":[{"time":0,"color":"ffffff00"}]},"huaban4":{"color":[{"time":0,"color":"ffffff00"}]},"huaban5":{"color":[{"time":0,"color":"ffffff00"}]},"huaban6":{"color":[{"time":0,"color":"ffffff00"}]},"huaban7":{"color":[{"time":0,"color":"ffffff00"}]},"huaban8":{"color":[{"time":0,"color":"ffffff00"}]},"huaban9":{"color":[{"time":0,"color":"ffffff00"}]},"光圈":{"color":[{"time":0,"color":"ffffff00"}]},"光束":{"color":[{"time":0,"color":"ffffff00"}]},"光束2":{"color":[{"time":0,"color":"ffffff00"}]},"光束3":{"color":[{"time":0,"color":"ffffff00"}]},"光束4":{"color":[{"time":0,"color":"ffffff00"}]},"光束5":{"color":[{"time":0,"color":"ffffff00"}]},"光束6":{"color":[{"time":0,"color":"ffffff00"}]},"光柱":{"color":[{"time":0,"color":"ffffff00"}]},"光柱2":{"color":[{"time":0,"color":"ffffff00"}]},"光柱3":{"color":[{"time":0,"color":"ffffff00"}]},"光柱4":{"color":[{"time":0,"color":"ffffff00"}]},"光柱5":{"color":[{"time":0,"color":"ffffff00"}]},"功 副本":{"color":[{"time":0,"color":"ffffffff"}]},"功 边框2":{"color":[{"time":0,"color":"ffffff00"}]},"升 副本":{"color":[{"time":0,"color":"ffffffff"}]},"升 边框2":{"color":[{"time":0,"color":"ffffff00"}]},"图层 1":{"color":[{"time":0,"color":"ffffffff"}]},"成 副本":{"color":[{"time":0,"color":"ffffffff"}]},"成 边框2":{"color":[{"time":0,"color":"ffffff00"}]},"晋 副本":{"color":[{"time":0,"color":"ffffffff"}]},"晋 边框2":{"color":[{"time":0,"color":"ffffff00"}]},"白光":{"color":[{"time":0,"color":"ffffff00"}]},"蝴蝶1":{"color":[{"time":0,"color":"ffffff00"}]},"蝴蝶2":{"color":[{"time":0,"color":"ffffff00"}]},"蝴蝶3":{"color":[{"time":0,"color":"ffffff00"}]},"蝴蝶5":{"color":[{"time":0,"color":"ffffff00"}]},"蝴蝶6":{"color":[{"time":0,"color":"ffffff00"}]},"蝴蝶7":{"color":[{"time":0,"color":"ffffff00"}]},"蝴蝶8":{"color":[{"time":0,"color":"ffffff00"}]},"蝴蝶9":{"color":[{"time":0,"color":"ffffff00"}]},"蝴蝶10":{"color":[{"time":0,"color":"ffffff00"}]},"蝴蝶1-1":{"color":[{"time":0,"color":"ffffff00"}]},"蝴蝶1-2":{"color":[{"time":0,"color":"ffffff00"}]},"蝴蝶1-3":{"color":[{"time":0,"color":"ffffff00"}]},"蝴蝶1-4":{"color":[{"time":0,"color":"ffffff00"}]},"蝴蝶1-5":{"color":[{"time":0,"color":"ffffff00"}]},"蝴蝶1-6":{"color":[{"time":0,"color":"ffffff00"}]},"蝴蝶1-7":{"color":[{"time":0,"color":"ffffff00"}]},"蝴蝶1-8":{"color":[{"time":0,"color":"ffffff00"}]},"蝴蝶1-9":{"color":[{"time":0,"color":"ffffff00"}]},"蝴蝶1-10":{"color":[{"time":0,"color":"ffffff00"}]},"蝴蝶2-1":{"color":[{"time":0,"color":"ffffff00"}]},"蝴蝶2-2":{"color":[{"time":0,"color":"ffffff00"}]},"蝴蝶2-3":{"color":[{"time":0,"color":"ffffff00"}]},"蝴蝶2-4":{"color":[{"time":0,"color":"ffffff00"}]},"蝴蝶2-7":{"color":[{"time":0,"color":"ffffff00"}]},"蝴蝶2-8":{"color":[{"time":0,"color":"ffffff00"}]},"蝴蝶2-9":{"color":[{"time":0,"color":"ffffff00"}]},"蝴蝶2-10":{"color":[{"time":0,"color":"ffffff00"}]},"闪光3":{"color":[{"time":0,"color":"ffffff00"}]},"闪光4":{"color":[{"time":0,"color":"ffffff00"}]},"闪光5":{"color":[{"time":0,"color":"ffffff00"}]},"闪光6":{"color":[{"time":0,"color":"ffffff00"}]},"闪光7":{"color":[{"time":0,"color":"ffffff00"}]},"闪光8":{"color":[{"time":0,"color":"ffffff00"}]},"闪光9":{"color":[{"time":0,"color":"ffffff00"}]},"闪光10":{"color":[{"time":0,"color":"ffffff00"}]},"闪光11":{"color":[{"time":0,"color":"ffffff00"}]},"闪光12":{"color":[{"time":0,"color":"ffffff00"}]},"闪光13":{"color":[{"time":0,"color":"ffffff00"}]},"闪光14":{"color":[{"time":0,"color":"ffffff00"}]},"闪光15":{"color":[{"time":0,"color":"ffffff00"}]},"闪光16":{"color":[{"time":0,"color":"ffffff00"}]},"闪光17":{"color":[{"time":0,"color":"ffffff00"}]}},"bones":{"光柱群":{"rotate":[{"time":0,"angle":0}],"translate":[{"time":0,"x":0,"y":0}],"scale":[{"time":0,"x":1,"y":1}],"shear":[{"time":0,"x":0,"y":0}]},"花瓣群":{"rotate":[{"time":0,"angle":0}],"translate":[{"time":0,"x":0,"y":0}],"scale":[{"time":0,"x":1,"y":1}],"shear":[{"time":0,"x":0,"y":0}]},"光柱2":{"rotate":[{"time":0,"angle":0}],"translate":[{"time":0,"x":-370.12,"y":0}],"scale":[{"time":0,"x":1,"y":1}],"shear":[{"time":0,"x":0,"y":0}]},"光束群":{"rotate":[{"time":0,"angle":0}],"translate":[{"time":0,"x":0,"y":0}],"scale":[{"time":0,"x":1,"y":1}],"shear":[{"time":0,"x":0,"y":0}]},"蝴蝶群":{"rotate":[{"time":0,"angle":0}],"translate":[{"time":0,"x":357.02,"y":699.07}],"scale":[{"time":0,"x":1,"y":1}],"shear":[{"time":0,"x":0,"y":0}]},"光柱4":{"rotate":[{"time":0,"angle":0}],"translate":[{"time":0,"x":-690.78,"y":0}],"scale":[{"time":0,"x":1,"y":1}],"shear":[{"time":0,"x":0,"y":0}]},"星星":{"rotate":[{"time":0,"angle":0}],"translate":[{"time":0,"x":-96.93,"y":7.2}],"scale":[{"time":0,"x":1.4,"y":1.4}],"shear":[{"time":0,"x":0,"y":0}]},"光柱3":{"rotate":[{"time":0,"angle":0}],"translate":[{"time":0,"x":357,"y":0}],"scale":[{"time":0,"x":1,"y":1}],"shear":[{"time":0,"x":0,"y":0}]},"晋升成功":{"rotate":[{"time":0,"angle":0}],"translate":[{"time":0,"x":0,"y":-308.7}],"scale":[{"time":0,"x":1,"y":1}],"shear":[{"time":0,"x":0,"y":0}]},"hit":{"rotate":[{"time":0,"angle":0}],"translate":[{"time":0,"x":0,"y":0}],"scale":[{"time":0,"x":1,"y":1}],"shear":[{"time":0,"x":0,"y":0}]},"光柱5":{"rotate":[{"time":0,"angle":0}],"translate":[{"time":0,"x":782.18,"y":0}],"scale":[{"time":0,"x":1,"y":1}],"shear":[{"time":0,"x":0,"y":0}]},"光圈":{"rotate":[{"time":0,"angle":0}],"translate":[{"time":0,"x":0,"y":0}],"scale":[{"time":0,"x":2.2,"y":2.2}],"shear":[{"time":0,"x":0,"y":0}]}}}}}